universal_gates/nor/design.v
`ifndef UNIVERSAL_GATES_NOR_DESIGN_V
`define UNIVERSAL_GATES_NOR_DESIGN_V

// Design of a NOR gate using PMOS and NMOS transistors
module nor_gate (
    a,
    b,
    out
);

    input a, b;
    output out;

    supply1 vcc;
    supply0 gnd;

    wire w1;

    pmos p1 (w1, vcc, a);
    pmos p2 (out, w1, b);

    nmos n1 (out, gnd, a);
    nmos n2 (out, gnd, b);

endmodule

`endif

gates_by_universal_gates/and/design.v
`include "/home/jack/struent_semiconductors_intern/universal_gates/nor/design.v"
`include "/home/jack/struent_semiconductors_intern/universal_gates/nand/design.v"

// AND gate implemented using NAND gates
module and_by_nand (
    a,
    b,
    out
);

    input a, b;
    output out;
    wire nand_out;

    nand_gate nand1 (
        .a  (a),
        .b  (b),
        .out(nand_out)
    );

    nand_gate nand2 (
        .a  (nand_out),
        .b  (nand_out),
        .out(out)
    );

endmodule


// AND gate implemented using NOR gates
module and_by_nor(
    a,
    b,
    out
);

    input a, b;
    output out;
    wire nor1_out;
    wire nor2_out;

    nor_gate nor1 (
        .a  (a),
        .b  (a),
        .out(nor1_out)
    );

    nor_gate nor2 (
        .a  (b),
        .b  (b),
        .out(nor2_out)
    );

    nor_gate nor3 (
        .a  (nor1_out),
        .b  (nor2_out),
        .out(out)
    );

endmodule

universal_gates/nand/design.v
// Design of a NAND gate using PMOS and NMOS transistors
module nand_gate(
    a,
    b,
    out
);
    input a,b;
    output out;

    supply1 vcc;
    supply0 gnd;

    wire w1;

    pmos p1(out, vcc, a);
    pmos p2(out, vcc, b);

    nmos n1(out, w1, a);
    nmos n2(w1, gnd, b);

endmodule

gates_by_universal_gates/and/testbench.v
module and_by_nand_nor_tb;

    reg nand_a, nand_b;
    wire nand_out;

    reg nor_a, nor_b;
    wire nor_out;

    and_by_nand and_gate (
        .a  (nand_a),
        .b  (nand_b),
        .out(nand_out)
    );

    and_by_nor and_gate2 (
        .a  (nor_a),
        .b  (nor_b),
        .out(nor_out)
    );


    initial begin


        $dumpfile("wave.vcd");
        $dumpvars(0, and_by_nand_nor_tb);

        for (integer i = 0; i < 4; i = i + 1) begin
            nand_a = i[1];
            nand_b = i[0];
            #10;
            $display("AND_BY_NAND ---  a: %b, b: %b, out: %b", nand_a, nand_b,
                     nand_out);
        end

        $write("\n");

        for (integer i = 0; i < 4; i = i + 1) begin
            nor_a = i[1];
            nor_b = i[0];
            #10;
            $display("AND_BY_NOR ---  a: %b, b: %b, out: %b", nor_a, nor_b, nor_out);
        end

        $finish;

    end

endmodule

gates_by_universal_gates/and/wave.vcd
$date
	Fri Apr 10 11:37:43 2026
$end
$version
	Icarus Verilog
$end
$timescale
	1s
$end
$scope module and_by_nand_nor_tb $end
$var wire 1 ! nand_out $end
$var wire 1 " nor_out $end
$var reg 1 # nand_a $end
$var reg 1 $ nand_b $end
$var reg 1 % nor_a $end
$var reg 1 & nor_b $end
$scope module and_gate $end
$var wire 1 # a $end
$var wire 1 $ b $end
$var wire 1 ' nand_out $end
$var wire 1 ! out $end
$scope module nand1 $end
$var wire 1 # a $end
$var wire 1 $ b $end
$var wire 1 ( gnd $end
$var wire 1 ' out $end
$var wire 1 ) vcc $end
$var wire 1 * w1 $end
$upscope $end
$scope module nand2 $end
$var wire 1 ' a $end
$var wire 1 ' b $end
$var wire 1 + gnd $end
$var wire 1 ! out $end
$var wire 1 , vcc $end
$var wire 1 - w1 $end
$upscope $end
$upscope $end
$scope module and_gate2 $end
$var wire 1 % a $end
$var wire 1 & b $end
$var wire 1 . nor1_out $end
$var wire 1 / nor2_out $end
$var wire 1 " out $end
$scope module nor1 $end
$var wire 1 % a $end
$var wire 1 % b $end
$var wire 1 0 gnd $end
$var wire 1 . out $end
$var wire 1 1 vcc $end
$var wire 1 2 w1 $end
$upscope $end
$scope module nor2 $end
$var wire 1 & a $end
$var wire 1 & b $end
$var wire 1 3 gnd $end
$var wire 1 / out $end
$var wire 1 4 vcc $end
$var wire 1 5 w1 $end
$upscope $end
$scope module nor3 $end
$var wire 1 . a $end
$var wire 1 / b $end
$var wire 1 6 gnd $end
$var wire 1 " out $end
$var wire 1 7 vcc $end
$var wire 1 8 w1 $end
$upscope $end
$upscope $end
$scope begin $ivl_for_loop0 $end
$var integer 32 9 i [31:0] $end
$upscope $end
$scope begin $ivl_for_loop1 $end
$var integer 32 : i [31:0] $end
$upscope $end
$upscope $end
$enddefinitions $end
$comment Show the parameter values. $end
$dumpall
$end
#0
$dumpvars
bx :
b0 9
x8
17
06
x5
14
03
x2
11
00
x/
x.
0-
1,
0+
z*
1)
0(
1'
x&
x%
0$
0#
x"
0!
$end
#10
0*
1$
b1 9
#20
z*
0$
0!
0-
1'
1#
b10 9
#30
1!
z-
0'
0*
1$
b11 9
#40
15
1/
0&
0"
12
z8
1.
0%
b0 :
b100 9
#50
z5
0/
1&
b1 :
#60
15
1/
0&
z2
18
0"
0.
1%
b10 :
#70
z5
1"
0/
1&
b11 :
#80
b100 :
