muxes/2x1/design.v
`ifndef MUX2X1_DESIGN_V
`define MUX2X1_DESIGN_V

module mux2x1(
    in,
    sel,
    out,
);
    input [1:0] in;
    input sel;
    output out;

    assign out = sel ? in[1] : in[0];

endmodule

`endif

muxes/4x1/design.v
`include "/home/jack/struent_semiconductors_intern/muxes/2x1/design.v"

module mux4x1 (
    in,
    sel,
    out
);

    input [3:0] in;
    input [1:0] sel;
    output out;

    mux2x1 mux0(
        .in (in[1:0]),
        .sel(sel[0]),
        .out(out0)
    );

    mux2x1 mux1(
        .in (in[3:2]),
        .sel(sel[0]),
        .out(out1)
    );

    mux2x1 mux2(
        .in ({out1, out0}),
        .sel(sel[1]),
        .out(out)
    );

endmodule

muxes/8x1/design.v
`include "/home/jack/struent_semiconductors_intern/muxes/4x1/design.v"
`include "/home/jack/struent_semiconductors_intern/muxes/2x1/design.v"

module mux8x1(
    in,
    sel,
    out
);
    input [7:0] in;
    input [2:0] sel;
    output out;

    mux4x1 mux0(
        .in(in[3:0]),
        .sel(sel[1:0]),
        .out(out1)
    );

    mux4x1 mux1(
        .in(in[7:4]),
        .sel(sel[1:0]),
        .out(out2)
    );

    mux2x1 mux2(
        .in({out2, out1}),
        .sel(sel[2]),
        .out(out)
    );

endmodule

muxes/8x1/testbench.v
module testbench;
    reg [7:0] in;
    reg [2:0] sel;
    wire out;

    mux8x1 uut (
        .in (in),
        .sel(sel),
        .out(out)
    );

    initial begin
        $dumpfile("wave.vcd");
        $dumpvars(0, testbench);

        $monitor("in: %b, sel: %b, out: %b", in, sel, out);

        in  = 8'b01010101;

        for (integer i = 0; i < 8; i = i + 1) begin
            sel = i[2:0];
            #10;
        end

        $finish;
    end
endmodule

muxes/8x1/wave.vcd
$date
	Mon Apr 13 11:53:39 2026
$end
$version
	Icarus Verilog
$end
$timescale
	1s
$end
$scope module testbench $end
$var wire 1 ! out $end
$var reg 8 " in [7:0] $end
$var reg 3 # sel [2:0] $end
$scope module uut $end
$var wire 8 $ in [7:0] $end
$var wire 3 % sel [2:0] $end
$var wire 1 & out2 $end
$var wire 1 ' out1 $end
$var wire 1 ! out $end
$scope module mux0 $end
$var wire 4 ( in [3:0] $end
$var wire 2 ) sel [1:0] $end
$var wire 1 * out1 $end
$var wire 1 + out0 $end
$var wire 1 ' out $end
$scope module mux0 $end
$var wire 2 , in [1:0] $end
$var wire 1 - sel $end
$var wire 1 + out $end
$upscope $end
$scope module mux1 $end
$var wire 2 . in [1:0] $end
$var wire 1 / sel $end
$var wire 1 * out $end
$upscope $end
$scope module mux2 $end
$var wire 2 0 in [1:0] $end
$var wire 1 1 sel $end
$var wire 1 ' out $end
$upscope $end
$upscope $end
$scope module mux1 $end
$var wire 4 2 in [3:0] $end
$var wire 2 3 sel [1:0] $end
$var wire 1 4 out1 $end
$var wire 1 5 out0 $end
$var wire 1 & out $end
$scope module mux0 $end
$var wire 2 6 in [1:0] $end
$var wire 1 7 sel $end
$var wire 1 5 out $end
$upscope $end
$scope module mux1 $end
$var wire 2 8 in [1:0] $end
$var wire 1 9 sel $end
$var wire 1 4 out $end
$upscope $end
$scope module mux2 $end
$var wire 2 : in [1:0] $end
$var wire 1 ; sel $end
$var wire 1 & out $end
$upscope $end
$upscope $end
$scope module mux2 $end
$var wire 2 < in [1:0] $end
$var wire 1 = sel $end
$var wire 1 ! out $end
$upscope $end
$upscope $end
$scope begin $ivl_for_loop0 $end
$var integer 32 > i [31:0] $end
$upscope $end
$upscope $end
$enddefinitions $end
$comment Show the parameter values. $end
$dumpall
$end
#0
$dumpvars
b0 >
0=
b11 <
0;
b11 :
09
b1 8
07
b1 6
15
14
b0 3
b101 2
01
b11 0
0/
b1 .
0-
b1 ,
1+
1*
b0 )
b101 (
1'
1&
b0 %
b1010101 $
b0 #
b1010101 "
1!
$end
#10
0!
0'
b0 <
0&
0+
b0 0
0*
05
b0 :
04
1-
1/
17
19
b1 )
b1 3
b1 #
b1 %
b1 >
#20
1!
1'
b11 <
1&
1+
b11 0
1*
15
b11 :
14
0-
0/
11
07
09
1;
b10 )
b10 3
b10 #
b10 %
b10 >
#30
0!
0'
b0 <
0&
0+
b0 0
0*
05
b0 :
04
1-
1/
17
19
b11 )
b11 3
b11 #
b11 %
b11 >
#40
1!
1'
b11 <
1&
1+
b11 0
1*
15
b11 :
14
0-
0/
01
07
09
0;
b0 )
b0 3
1=
b100 #
b100 %
b100 >
#50
0!
0'
b0 <
0&
0+
b0 0
0*
05
b0 :
04
1-
1/
17
19
b1 )
b1 3
b101 #
b101 %
b101 >
#60
1!
1'
b11 <
1&
1+
b11 0
1*
15
b11 :
14
0-
0/
11
07
09
1;
b10 )
b10 3
b110 #
b110 %
b110 >
#70
0!
0'
b0 <
0&
0+
b0 0
0*
05
b0 :
04
1-
1/
17
19
b11 )
b11 3
b111 #
b111 %
b111 >
#80
b1000 >
