decoders/4x16/design.v
module decoder4x16 (
    input [3:0] in,
    output reg [15:0] out
);
    always @(*) begin
        out = 8'd0;

        for (integer i = 0; i < 16; i = i + 1) begin
            if (in == i) begin
                out[i] = 1'b1;
            end
        end

    end

endmodule

decoders/4x16/testbench.v
module testbench;

    reg  [ 3:0] in;
    wire [15:0] out;

    decoder4x16 uut (
        .in (in),
        .out(out)
    );

    initial begin
        $dumpfile("wave.vcd");
        $dumpvars(0, testbench);

        $monitor("in = %b, out = %b", in, out);

        for (integer i = 0; i < 16; i = i + 1) begin
            in = i[3:0];
            #10;
        end

        $finish;
    end

endmodule

decoders/4x16/wave.vcd
$date
	Mon Apr 20 16:34:43 2026
$end
$version
	Icarus Verilog
$end
$timescale
	1s
$end
$scope module testbench $end
$var wire 16 ! out [15:0] $end
$var reg 4 " in [3:0] $end
$scope module uut $end
$var wire 4 # in [3:0] $end
$var reg 16 $ out [15:0] $end
$scope begin $ivl_for_loop0 $end
$var integer 32 % i [31:0] $end
$upscope $end
$upscope $end
$scope begin $ivl_for_loop1 $end
$var integer 32 & i [31:0] $end
$upscope $end
$upscope $end
$enddefinitions $end
$comment Show the parameter values. $end
$dumpall
$end
#0
$dumpvars
b0 &
b10000 %
b1 $
b0 #
b0 "
b1 !
$end
#10
b10000 %
b10 !
b10 $
b1 "
b1 #
b1 &
#20
b10000 %
b100 !
b100 $
b10 "
b10 #
b10 &
#30
b10000 %
b1000 !
b1000 $
b11 "
b11 #
b11 &
#40
b10000 %
b10000 !
b10000 $
b100 "
b100 #
b100 &
#50
b10000 %
b100000 !
b100000 $
b101 "
b101 #
b101 &
#60
b10000 %
b1000000 !
b1000000 $
b110 "
b110 #
b110 &
#70
b10000 %
b10000000 !
b10000000 $
b111 "
b111 #
b111 &
#80
b10000 %
b100000000 !
b100000000 $
b1000 "
b1000 #
b1000 &
#90
b10000 %
b1000000000 !
b1000000000 $
b1001 "
b1001 #
b1001 &
#100
b10000 %
b10000000000 !
b10000000000 $
b1010 "
b1010 #
b1010 &
#110
b10000 %
b100000000000 !
b100000000000 $
b1011 "
b1011 #
b1011 &
#120
b10000 %
b1000000000000 !
b1000000000000 $
b1100 "
b1100 #
b1100 &
#130
b10000 %
b10000000000000 !
b10000000000000 $
b1101 "
b1101 #
b1101 &
#140
b10000 %
b100000000000000 !
b100000000000000 $
b1110 "
b1110 #
b1110 &
#150
b10000 %
b1000000000000000 !
b1000000000000000 $
b1111 "
b1111 #
b1111 &
#160
b10000 &
