demuxes/1x2/design.v
module demux1x2 (
    in,
    sel,
    out
);
    input in, sel;
    output [1:0] out;

    assign out[0] = in & ~sel;
    assign out[1] = in & sel;

endmodule

demuxes/1x4/design.v
`include "/home/jack/struent_semiconductors_intern/demuxes/1x2/design.v"

module demux1x4 (
    in,
    sel,
    out
);
    input in;
    input [1:0] sel;
    output [3:0] out;
    wire [1:0] out1;

    demux1x2 demux0 (
        .in (in),
        .sel(sel[1]),
        .out(out1)
    );

    demux1x2 demux1 (
        .in (out1[0]),
        .sel(sel[0]),
        .out(out[1:0])
    );

    demux1x2 demux2 (
        .in (out1[1]),
        .sel(sel[0]),
        .out(out[3:2])
    );

endmodule

demuxes/1x8/design.v
`include "/home/jack/struent_semiconductors_intern/demuxes/1x4/design.v"
`include "/home/jack/struent_semiconductors_intern/demuxes/1x2/design.v"

module demux1x8 (
    in,
    sel,
    out
);
    input in;
    input [2:0] sel;
    output [7:0] out;
    wire [1:0] out1;

    demux1x2 demux0 (
        .in (in),
        .sel(sel[2]),
        .out(out1)
    );

    demux1x4 demux1 (
        .in (out1[0]),
        .sel(sel[1:0]),
        .out(out[3:0])
    );

    demux1x4 demux2 (
        .in (out1[1]),
        .sel(sel[1:0]),
        .out(out[7:4])
    );

endmodule

demuxes/1x8/testbench.v
module testbench;
    reg in;
    reg [2:0] sel;
    wire [7:0] out;

    demux1x8 dut (
        .in (in),
        .sel(sel),
        .out(out)
    );

    initial begin
        $dumpfile("wave.vcd");
        $dumpvars(0, testbench);

        $monitor("in=%b, sel=%b, out=%b", in, sel, out);

        in = 1;

        for (integer i = 0; i < 8; i++) begin
            sel = i[2:0];
            #10;
        end

        $finish;
    end
endmodule

demuxes/1x8/wave.vcd
$date
	Mon Apr 13 12:45:15 2026
$end
$version
	Icarus Verilog
$end
$timescale
	1s
$end
$scope module testbench $end
$var wire 8 ! out [7:0] $end
$var reg 1 " in $end
$var reg 3 # sel [2:0] $end
$scope module dut $end
$var wire 1 " in $end
$var wire 3 $ sel [2:0] $end
$var wire 2 % out1 [1:0] $end
$var wire 8 & out [7:0] $end
$scope module demux0 $end
$var wire 1 " in $end
$var wire 1 ' sel $end
$var wire 2 ( out [1:0] $end
$upscope $end
$scope module demux1 $end
$var wire 1 ) in $end
$var wire 2 * sel [1:0] $end
$var wire 2 + out1 [1:0] $end
$var wire 4 , out [3:0] $end
$scope module demux0 $end
$var wire 1 ) in $end
$var wire 1 - sel $end
$var wire 2 . out [1:0] $end
$upscope $end
$scope module demux1 $end
$var wire 1 / in $end
$var wire 1 0 sel $end
$var wire 2 1 out [1:0] $end
$upscope $end
$scope module demux2 $end
$var wire 1 2 in $end
$var wire 1 3 sel $end
$var wire 2 4 out [1:0] $end
$upscope $end
$upscope $end
$scope module demux2 $end
$var wire 1 5 in $end
$var wire 2 6 sel [1:0] $end
$var wire 2 7 out1 [1:0] $end
$var wire 4 8 out [3:0] $end
$scope module demux0 $end
$var wire 1 5 in $end
$var wire 1 9 sel $end
$var wire 2 : out [1:0] $end
$upscope $end
$scope module demux1 $end
$var wire 1 ; in $end
$var wire 1 < sel $end
$var wire 2 = out [1:0] $end
$upscope $end
$scope module demux2 $end
$var wire 1 > in $end
$var wire 1 ? sel $end
$var wire 2 @ out [1:0] $end
$upscope $end
$upscope $end
$upscope $end
$scope begin $ivl_for_loop0 $end
$var integer 32 A i [31:0] $end
$upscope $end
$upscope $end
$enddefinitions $end
$comment Show the parameter values. $end
$dumpall
$end
#0
$dumpvars
b0 A
b0 @
0?
0>
b0 =
0<
0;
b0 :
09
b0 8
b0 7
b0 6
05
b0 4
03
02
b1 1
00
1/
b1 .
0-
b1 ,
b1 +
b0 *
1)
b1 (
0'
b1 &
b1 %
b0 $
b0 #
1"
b1 !
$end
#10
b10 !
b10 &
b10 ,
b10 1
10
13
1<
1?
b1 *
b1 6
b1 #
b1 $
b1 A
#20
0/
b1 4
12
b10 +
b10 .
b100 !
b100 &
b100 ,
b0 1
1-
00
03
19
0<
0?
b10 *
b10 6
b10 #
b10 $
b10 A
#30
b1000 !
b1000 &
b1000 ,
b10 4
10
13
1<
1?
b11 *
b11 6
b11 #
b11 $
b11 A
#40
b0 1
b1 8
b1 =
0/
1;
0)
02
b1 7
b1 :
15
b0 +
b0 .
b10000 !
b10000 &
b0 ,
b0 4
b10 %
b10 (
0-
00
03
09
0<
0?
1'
b0 *
b0 6
b100 #
b100 $
b100 A
#50
b100000 !
b100000 &
b10 8
b10 =
10
13
1<
1?
b1 *
b1 6
b101 #
b101 $
b101 A
#60
0;
b1 @
1>
b10 7
b10 :
b1000000 !
b1000000 &
b100 8
b0 =
1-
00
03
19
0<
0?
b10 *
b10 6
b110 #
b110 $
b110 A
#70
b10000000 !
b10000000 &
b1000 8
b10 @
10
13
1<
1?
b11 *
b11 6
b111 #
b111 $
b111 A
#80
b1000 A
