octal_to_binary/design.v
module octal_to_binary (
    input [7:0] in,
    output reg [2:0] out
);

    always @(*) begin
        out = 3'd0;

        out[2] = in[4] | in[5] | in[6] | in[7];

        out[1] = in[2] | in[3] | in[6] | in[7];

        out[0] = in[1] | in[3] | in[5] | in[7];

    end

endmodule

octal_to_binary/testbench.v
module testbench;
    reg [7:0] in;
    wire [2:0] out;
    integer i;

    octal_to_binary uut (
        .in (in),
        .out(out)
    );

    initial begin
        $dumpfile("wave.vcd");
        $dumpvars(0, testbench);

        for (i = 0; i < 8; i++) begin
            in = 8'd0;
            in[i] = 1;

            #15;
            $display("in = %b or %d | out = %b", in, i[2:0], out);
        end

        $finish;
    end

endmodule

octal_to_binary/wave.vcd
$date
	Wed Apr 22 15:13:40 2026
$end
$version
	Icarus Verilog
$end
$timescale
	1s
$end
$scope module testbench $end
$var wire 3 ! out [2:0] $end
$var reg 8 " in [7:0] $end
$var integer 32 # i [31:0] $end
$scope module uut $end
$var wire 8 $ in [7:0] $end
$var reg 3 % out [2:0] $end
$upscope $end
$upscope $end
$enddefinitions $end
$comment Show the parameter values. $end
$dumpall
$end
#0
$dumpvars
b0 %
b1 $
b0 #
b1 "
b0 !
$end
#15
b1 !
b1 %
b10 "
b10 $
b1 #
#30
b10 !
b10 %
b100 "
b100 $
b10 #
#45
b11 !
b11 %
b1000 "
b1000 $
b11 #
#60
b100 !
b100 %
b10000 "
b10000 $
b100 #
#75
b101 !
b101 %
b100000 "
b100000 $
b101 #
#90
b110 !
b110 %
b1000000 "
b1000000 $
b110 #
#105
b111 !
b111 %
b10000000 "
b10000000 $
b111 #
#120
b1000 #
