decoders/priority_decoders/2x4/design.v
module priority_decoder2x4_LSB (
    input [1:0] in,
    output reg [3:0] out
);

    always @(*) begin
        out = 4'd0;

        for (integer i = 0; i < 4; i++) begin
            if (in == i) begin
                out[i] = 1;
            end
        end

    end

endmodule


module priority_decoder2x4_MSB (
    input [1:0] in,
    output reg [3:0] out
);

    always @(*) begin
        out = 4'd0;

        for (integer i = 3; i >= 0; i--) begin
            if (in == i) begin
                out[i] = 1;
            end
        end

    end

endmodule

decoders/priority_decoders/2x4/testbench.v
module testbench;

    reg  [1:0] lsb_in;
    wire [3:0] lsb_out;

    reg  [1:0] msb_in;
    wire [3:0] msb_out;

    priority_decoder2x4_LSB uut (
        .in (lsb_in),
        .out(lsb_out)
    );

    priority_decoder2x4_MSB uut2 (
        .in (msb_in),
        .out(msb_out)
    );

    initial begin
        $dumpfile("wave.vcd");
        $dumpvars(0, testbench);

        for (integer i = 0; i < 4; i++) begin
            lsb_in = i[1:0];
            #15;
            $display("LSB: in = %b | out = %b", lsb_in, lsb_out);

        end

        $write("\n");

        for (integer i = 0; i < 4; i++) begin
            msb_in = i[1:0];
            #15;
            $display("MSB: in = %b | out = %b", msb_in, msb_out);
        end

        $finish;
    end
endmodule

decoders/priority_decoders/2x4/wave.vcd
$date
	Wed Apr 22 11:44:33 2026
$end
$version
	Icarus Verilog
$end
$timescale
	1s
$end
$scope module testbench $end
$var wire 4 ! msb_out [3:0] $end
$var wire 4 " lsb_out [3:0] $end
$var reg 2 # lsb_in [1:0] $end
$var reg 2 $ msb_in [1:0] $end
$scope module uut $end
$var wire 2 % in [1:0] $end
$var reg 4 & out [3:0] $end
$scope begin $ivl_for_loop0 $end
$var integer 32 ' i [31:0] $end
$upscope $end
$upscope $end
$scope module uut2 $end
$var wire 2 ( in [1:0] $end
$var reg 4 ) out [3:0] $end
$scope begin $ivl_for_loop1 $end
$var integer 32 * i [31:0] $end
$upscope $end
$upscope $end
$scope begin $ivl_for_loop2 $end
$var integer 32 + i [31:0] $end
$upscope $end
$scope begin $ivl_for_loop3 $end
$var integer 32 , i [31:0] $end
$upscope $end
$upscope $end
$enddefinitions $end
$comment Show the parameter values. $end
$dumpall
$end
#0
$dumpvars
bx ,
b0 +
bx *
bx )
bx (
b100 '
b1 &
b0 %
bx $
b0 #
b1 "
bx !
$end
#15
b100 '
b10 "
b10 &
b1 #
b1 %
b1 +
#30
b100 '
b100 "
b100 &
b10 #
b10 %
b10 +
#45
b100 '
b1000 "
b1000 &
b11 #
b11 %
b11 +
#60
b11111111111111111111111111111111 *
b1 !
b1 )
b0 $
b0 (
b0 ,
b100 +
#75
b11111111111111111111111111111111 *
b10 !
b10 )
b1 $
b1 (
b1 ,
#90
b11111111111111111111111111111111 *
b100 !
b100 )
b10 $
b10 (
b10 ,
#105
b11111111111111111111111111111111 *
b1000 !
b1000 )
b11 $
b11 (
b11 ,
#120
b100 ,
