muxes/2x1/design.v
`ifndef MUX2X1_DESIGN_V
`define MUX2X1_DESIGN_V

module mux2x1(
    in,
    sel,
    out,
);
    input [1:0] in;
    input sel;
    output out;

    assign out = sel ? in[1] : in[0];

endmodule

`endif

muxes/4x1/design.v
`include "/home/jack/struent_semiconductors_intern/muxes/2x1/design.v"

module mux4x1 (
    in,
    sel,
    out
);

    input [3:0] in;
    input [1:0] sel;
    wire out0, out1;
    output out;

    mux2x1 mux0(
        .in (in[1:0]),
        .sel(sel[0]),
        .out(out0)
    );

    mux2x1 mux1(
        .in (in[3:2]),
        .sel(sel[0]),
        .out(out1)
    );

    mux2x1 mux2(
        .in ({out1, out0}),
        .sel(sel[1]),
        .out(out)
    );

endmodule

muxes/8x1/design.v
`include "/home/jack/struent_semiconductors_intern/muxes/4x1/design.v"
`include "/home/jack/struent_semiconductors_intern/muxes/2x1/design.v"

module mux8x1(
    in,
    sel,
    out
);
    input [7:0] in;
    input [2:0] sel;
    wire out1, out2;
    output out;

    mux4x1 mux0(
        .in(in[3:0]),
        .sel(sel[1:0]),
        .out(out1)
    );

    mux4x1 mux1(
        .in(in[7:4]),
        .sel(sel[1:0]),
        .out(out2)
    );

    mux2x1 mux2(
        .in({out2, out1}),
        .sel(sel[2]),
        .out(out)
    );

endmodule

muxes/16x1/design.v
`include "/home/jack/struent_semiconductors_intern/muxes/8x1/design.v"
`include "/home/jack/struent_semiconductors_intern/muxes/2x1/design.v"

module mux16x1(
    in,
    sel,
    out
);
    input [15:0] in;
    input [3:0] sel;
    wire out1, out2;
    output out;

    mux8x1 mux0(
        .in(in[7:0]),
        .sel(sel[2:0]),
        .out(out1)
    );

    mux8x1 mux1(
        .in(in[15:8]),
        .sel(sel[2:0]),
        .out(out2)
    );

    mux2x1 mux2(
        .in({out2, out1}),
        .sel(sel[3]),
        .out(out)
    );

endmodule

muxes/16x1/testbench.v
module testbench;
    reg [15:0] in;
    reg [3:0] sel;
    wire out;

    mux16x1 uut (
        .in (in),
        .sel(sel),
        .out(out)
    );

    initial begin
        $dumpfile("wave.vcd");
        $dumpvars(0, testbench);

        $monitor("in: %b, sel: %b, out: %b", in, sel, out);

        in  = 16'b0101010101010101;

        for (integer i = 0; i < 16; i = i + 1) begin
            sel = i[3:0];
            #10;
        end

        $finish;
    end
endmodule

muxes/16x1/wave.vcd
$date
	Mon Apr 13 11:57:52 2026
$end
$version
	Icarus Verilog
$end
$timescale
	1s
$end
$scope module testbench $end
$var wire 1 ! out $end
$var reg 16 " in [15:0] $end
$var reg 4 # sel [3:0] $end
$scope module uut $end
$var wire 16 $ in [15:0] $end
$var wire 4 % sel [3:0] $end
$var wire 1 & out2 $end
$var wire 1 ' out1 $end
$var wire 1 ! out $end
$scope module mux0 $end
$var wire 8 ( in [7:0] $end
$var wire 3 ) sel [2:0] $end
$var wire 1 * out2 $end
$var wire 1 + out1 $end
$var wire 1 ' out $end
$scope module mux0 $end
$var wire 4 , in [3:0] $end
$var wire 2 - sel [1:0] $end
$var wire 1 . out1 $end
$var wire 1 / out0 $end
$var wire 1 + out $end
$scope module mux0 $end
$var wire 2 0 in [1:0] $end
$var wire 1 1 sel $end
$var wire 1 / out $end
$upscope $end
$scope module mux1 $end
$var wire 2 2 in [1:0] $end
$var wire 1 3 sel $end
$var wire 1 . out $end
$upscope $end
$scope module mux2 $end
$var wire 2 4 in [1:0] $end
$var wire 1 5 sel $end
$var wire 1 + out $end
$upscope $end
$upscope $end
$scope module mux1 $end
$var wire 4 6 in [3:0] $end
$var wire 2 7 sel [1:0] $end
$var wire 1 8 out1 $end
$var wire 1 9 out0 $end
$var wire 1 * out $end
$scope module mux0 $end
$var wire 2 : in [1:0] $end
$var wire 1 ; sel $end
$var wire 1 9 out $end
$upscope $end
$scope module mux1 $end
$var wire 2 < in [1:0] $end
$var wire 1 = sel $end
$var wire 1 8 out $end
$upscope $end
$scope module mux2 $end
$var wire 2 > in [1:0] $end
$var wire 1 ? sel $end
$var wire 1 * out $end
$upscope $end
$upscope $end
$scope module mux2 $end
$var wire 2 @ in [1:0] $end
$var wire 1 A sel $end
$var wire 1 ' out $end
$upscope $end
$upscope $end
$scope module mux1 $end
$var wire 8 B in [7:0] $end
$var wire 3 C sel [2:0] $end
$var wire 1 D out2 $end
$var wire 1 E out1 $end
$var wire 1 & out $end
$scope module mux0 $end
$var wire 4 F in [3:0] $end
$var wire 2 G sel [1:0] $end
$var wire 1 H out1 $end
$var wire 1 I out0 $end
$var wire 1 E out $end
$scope module mux0 $end
$var wire 2 J in [1:0] $end
$var wire 1 K sel $end
$var wire 1 I out $end
$upscope $end
$scope module mux1 $end
$var wire 2 L in [1:0] $end
$var wire 1 M sel $end
$var wire 1 H out $end
$upscope $end
$scope module mux2 $end
$var wire 2 N in [1:0] $end
$var wire 1 O sel $end
$var wire 1 E out $end
$upscope $end
$upscope $end
$scope module mux1 $end
$var wire 4 P in [3:0] $end
$var wire 2 Q sel [1:0] $end
$var wire 1 R out1 $end
$var wire 1 S out0 $end
$var wire 1 D out $end
$scope module mux0 $end
$var wire 2 T in [1:0] $end
$var wire 1 U sel $end
$var wire 1 S out $end
$upscope $end
$scope module mux1 $end
$var wire 2 V in [1:0] $end
$var wire 1 W sel $end
$var wire 1 R out $end
$upscope $end
$scope module mux2 $end
$var wire 2 X in [1:0] $end
$var wire 1 Y sel $end
$var wire 1 D out $end
$upscope $end
$upscope $end
$scope module mux2 $end
$var wire 2 Z in [1:0] $end
$var wire 1 [ sel $end
$var wire 1 & out $end
$upscope $end
$upscope $end
$scope module mux2 $end
$var wire 2 \ in [1:0] $end
$var wire 1 ] sel $end
$var wire 1 ! out $end
$upscope $end
$upscope $end
$scope begin $ivl_for_loop0 $end
$var integer 32 ^ i [31:0] $end
$upscope $end
$upscope $end
$enddefinitions $end
$comment Show the parameter values. $end
$dumpall
$end
#0
$dumpvars
b0 ^
0]
b11 \
0[
b11 Z
0Y
b11 X
0W
b1 V
0U
b1 T
1S
1R
b0 Q
b101 P
0O
b11 N
0M
b1 L
0K
b1 J
1I
1H
b0 G
b101 F
1E
1D
b0 C
b1010101 B
0A
b11 @
0?
b11 >
0=
b1 <
0;
b1 :
19
18
b0 7
b101 6
05
b11 4
03
b1 2
01
b1 0
1/
1.
b0 -
b101 ,
1+
1*
b0 )
b1010101 (
1'
1&
b0 %
b101010101010101 $
b0 #
b101010101010101 "
1!
$end
#10
0!
0'
b0 \
0&
0+
b0 @
0*
0E
b0 Z
0D
0/
b0 4
0.
09
b0 >
08
0I
b0 N
0H
0S
b0 X
0R
11
13
1;
1=
1K
1M
1U
1W
b1 -
b1 7
b1 G
b1 Q
b1 )
b1 C
b1 #
b1 %
b1 ^
#20
1!
1'
b11 \
1&
1+
b11 @
1*
1E
b11 Z
1D
1/
b11 4
1.
19
b11 >
18
1I
b11 N
1H
1S
b11 X
1R
01
03
15
0;
0=
1?
0K
0M
1O
0U
0W
1Y
b10 -
b10 7
b10 G
b10 Q
b10 )
b10 C
b10 #
b10 %
b10 ^
#30
0!
0'
b0 \
0&
0+
b0 @
0*
0E
b0 Z
0D
0/
b0 4
0.
09
b0 >
08
0I
b0 N
0H
0S
b0 X
0R
11
13
1;
1=
1K
1M
1U
1W
b11 -
b11 7
b11 G
b11 Q
b11 )
b11 C
b11 #
b11 %
b11 ^
#40
1!
1'
b11 \
1&
1+
b11 @
1*
1E
b11 Z
1D
1/
b11 4
1.
19
b11 >
18
1I
b11 N
1H
1S
b11 X
1R
01
03
05
0;
0=
0?
0K
0M
0O
0U
0W
0Y
b0 -
b0 7
1A
b0 G
b0 Q
1[
b100 )
b100 C
b100 #
b100 %
b100 ^
#50
0!
0'
b0 \
0&
0+
b0 @
0*
0E
b0 Z
0D
0/
b0 4
0.
09
b0 >
08
0I
b0 N
0H
0S
b0 X
0R
11
13
1;
1=
1K
1M
1U
1W
b1 -
b1 7
b1 G
b1 Q
b101 )
b101 C
b101 #
b101 %
b101 ^
#60
1!
1'
b11 \
1&
1+
b11 @
1*
1E
b11 Z
1D
1/
b11 4
1.
19
b11 >
18
1I
b11 N
1H
1S
b11 X
1R
01
03
15
0;
0=
1?
0K
0M
1O
0U
0W
1Y
b10 -
b10 7
b10 G
b10 Q
b110 )
b110 C
b110 #
b110 %
b110 ^
#70
0!
0'
b0 \
0&
0+
b0 @
0*
0E
b0 Z
0D
0/
b0 4
0.
09
b0 >
08
0I
b0 N
0H
0S
b0 X
0R
11
13
1;
1=
1K
1M
1U
1W
b11 -
b11 7
b11 G
b11 Q
b111 )
b111 C
b111 #
b111 %
b111 ^
#80
1!
1'
b11 \
1&
1+
b11 @
1*
1E
b11 Z
1D
1/
b11 4
1.
19
b11 >
18
1I
b11 N
1H
1S
b11 X
1R
01
03
05
0;
0=
0?
0K
0M
0O
0U
0W
0Y
b0 -
b0 7
0A
b0 G
b0 Q
0[
b0 )
b0 C
1]
b1000 #
b1000 %
b1000 ^
#90
0!
0'
b0 \
0&
0+
b0 @
0*
0E
b0 Z
0D
0/
b0 4
0.
09
b0 >
08
0I
b0 N
0H
0S
b0 X
0R
11
13
1;
1=
1K
1M
1U
1W
b1 -
b1 7
b1 G
b1 Q
b1 )
b1 C
b1001 #
b1001 %
b1001 ^
#100
1!
1'
b11 \
1&
1+
b11 @
1*
1E
b11 Z
1D
1/
b11 4
1.
19
b11 >
18
1I
b11 N
1H
1S
b11 X
1R
01
03
15
0;
0=
1?
0K
0M
1O
0U
0W
1Y
b10 -
b10 7
b10 G
b10 Q
b10 )
b10 C
b1010 #
b1010 %
b1010 ^
#110
0!
0'
b0 \
0&
0+
b0 @
0*
0E
b0 Z
0D
0/
b0 4
0.
09
b0 >
08
0I
b0 N
0H
0S
b0 X
0R
11
13
1;
1=
1K
1M
1U
1W
b11 -
b11 7
b11 G
b11 Q
b11 )
b11 C
b1011 #
b1011 %
b1011 ^
#120
1!
1'
b11 \
1&
1+
b11 @
1*
1E
b11 Z
1D
1/
b11 4
1.
19
b11 >
18
1I
b11 N
1H
1S
b11 X
1R
01
03
05
0;
0=
0?
0K
0M
0O
0U
0W
0Y
b0 -
b0 7
1A
b0 G
b0 Q
1[
b100 )
b100 C
b1100 #
b1100 %
b1100 ^
#130
0!
0'
b0 \
0&
0+
b0 @
0*
0E
b0 Z
0D
0/
b0 4
0.
09
b0 >
08
0I
b0 N
0H
0S
b0 X
0R
11
13
1;
1=
1K
1M
1U
1W
b1 -
b1 7
b1 G
b1 Q
b101 )
b101 C
b1101 #
b1101 %
b1101 ^
#140
1!
1'
b11 \
1&
1+
b11 @
1*
1E
b11 Z
1D
1/
b11 4
1.
19
b11 >
18
1I
b11 N
1H
1S
b11 X
1R
01
03
15
0;
0=
1?
0K
0M
1O
0U
0W
1Y
b10 -
b10 7
b10 G
b10 Q
b110 )
b110 C
b1110 #
b1110 %
b1110 ^
#150
0!
0'
b0 \
0&
0+
b0 @
0*
0E
b0 Z
0D
0/
b0 4
0.
09
b0 >
08
0I
b0 N
0H
0S
b0 X
0R
11
13
1;
1=
1K
1M
1U
1W
b11 -
b11 7
b11 G
b11 Q
b111 )
b111 C
b1111 #
b1111 %
b1111 ^
#160
b10000 ^
