universal_gates/nand/design.v
// Design of a NAND gate using PMOS and NMOS transistors
module nand_gate(
    a,
    b,
    out
);
    input a,b;
    output out;

    supply1 vcc;
    supply0 gnd;

    wire w1;

    pmos p1(out, vcc, a);
    pmos p2(out, vcc, b);

    nmos n1(out, w1, a);
    nmos n2(w1, gnd, b);

endmodule

gates_by_universal_gates/xor/design.v
`include "/home/jack/struent_semiconductors_intern/universal_gates/nor/design.v"
`include "/home/jack/struent_semiconductors_intern/universal_gates/nand/design.v"


// XOR gate implemented using NAND gates
module xor_by_nand (
    a,
    b,
    out
);

    input a, b;
    output out;

    wire nand1_out;
    wire nand2_out;
    wire nand3_out;

    nand_gate nand1(.a(a), .b(b), .out(nand1_out));
    nand_gate nand2(.a(a), .b(nand1_out), .out(nand2_out));
    nand_gate nand3(.a(nand1_out), .b(b), .out(nand3_out));
    nand_gate nand4(.a(nand2_out), .b(nand3_out), .out(out));

endmodule


// XOR gate implemented using NOR gates
module xor_by_nor (
    a,
    b,
    out
);
    
    input a, b;
    output out;

    wire nor1_out;
    wire nor2_out;
    wire nor3_out;
    wire nor4_out;

    nor_gate nor1(.a(a), .b(b), .out(nor1_out));
    nor_gate nor2(.a(a), .b(nor1_out), .out(nor2_out));
    nor_gate nor3(.a(nor1_out), .b(b), .out(nor3_out));
    nor_gate nor4(.a(nor2_out), .b(nor3_out), .out(nor4_out));
    nor_gate nor5(.a(nor4_out), .b(nor4_out), .out(out));

endmodule

gates_by_universal_gates/and/design.v
`include "/home/jack/struent_semiconductors_intern/universal_gates/nor/design.v"
`include "/home/jack/struent_semiconductors_intern/universal_gates/nand/design.v"

// AND gate implemented using NAND gates
module and_by_nand (
    a,
    b,
    out
);

    input a, b;
    output out;
    wire nand_out;

    nand_gate nand1 (
        .a  (a),
        .b  (b),
        .out(nand_out)
    );

    nand_gate nand2 (
        .a  (nand_out),
        .b  (nand_out),
        .out(out)
    );

endmodule


// AND gate implemented using NOR gates
module and_by_nor(
    a,
    b,
    out
);

    input a, b;
    output out;
    wire nor1_out;
    wire nor2_out;

    nor_gate nor1 (
        .a  (a),
        .b  (a),
        .out(nor1_out)
    );

    nor_gate nor2 (
        .a  (b),
        .b  (b),
        .out(nor2_out)
    );

    nor_gate nor3 (
        .a  (nor1_out),
        .b  (nor2_out),
        .out(out)
    );

endmodule

half_adder/design.v
`include "../gates_by_universal_gates/and/design.v"
`include "../gates_by_universal_gates/xor/design.v"

// Design of a half adder using data flow modeling
module half_adder_dataflow (
    a,
    b,
    sum,
    carry
);

    input a, b;
    output sum, carry;

    assign sum   = a ^ b;
    assign carry = a & b;

endmodule

// Design of a half adder using behavioural modeling
module half_adder_behavioural (
    a,
    b,
    sum,
    carry
);

    input a, b;
    output reg sum, carry;

    always @(a or b) begin
        sum   = a ^ b;
        carry = a & b;
    end

endmodule


// Design of a half adder using structural modeling
module half_adder_structural (
    a,
    b,
    sum,
    carry
);

    input a, b;
    output sum, carry;

    xor (sum, a, b);
    and (carry, a, b);

endmodule

// Design of a half adder using switch level modeling
module half_adder_switch_level (
    a,
    b,
    sum,
    carry
);

    input a, b;
    output sum, carry;

    and_by_nand and_gate (
        .a  (a),
        .b  (b),
        .out(carry)
    );

    xor_by_nand xor_gate (
        .a  (a),
        .b  (b),
        .out(sum)
    );

endmodule

half_adder/testbench.v
module half_adder_tb;
    reg df_a, df_b;
    wire df_sum, df_carry;

    reg bh_a, bh_b;
    wire bh_sum, bh_carry;

    reg gl_a, gl_b;
    wire gl_sum, gl_carry;

    reg sl_a, sl_b;
    wire sl_sum, sl_carry;

    half_adder_dataflow df (
        .a(df_a),
        .b(df_b),
        .sum(df_sum),
        .carry(df_carry)
    );

    half_adder_behavioural bh (
        .a(bh_a),
        .b(bh_b),
        .sum(bh_sum),
        .carry(bh_carry)
    );

    half_adder_structural gl (
        .a(gl_a),
        .b(gl_b),
        .sum(gl_sum),
        .carry(gl_carry)
    );

    half_adder_switch_level sl (
        .a(sl_a),
        .b(sl_b),
        .sum(sl_sum),
        .carry(sl_carry)
    );

    initial begin
        $dumpfile("wave.vcd");
        $dumpvars(0, half_adder_tb);

        for (integer i = 0; i < 4; i++) begin
            {df_a, df_b} = i[1:0];
            #10;

            $display("Dataflow: a=%b, b=%b, sum=%b, carry=%b", df_a, df_b,
                     df_sum, df_carry);
        end

        $write("\n");

        for (integer i = 0; i < 4; i++) begin
            {bh_a, bh_b} = i[1:0];
            #10;

            $display("Behavioural: a=%b, b=%b, sum=%b, carry=%b", bh_a, bh_b,
                     bh_sum, bh_carry);
        end

        $write("\n");

        for (integer i = 0; i < 4; i++) begin
            {gl_a, gl_b} = i[1:0];
            #10;

            $display("Gate-level: a=%b, b=%b, sum=%b, carry=%b", gl_a, gl_b,
                     gl_sum, gl_carry);
        end
        
        $write("\n");

        for (integer i = 0; i < 4; i++) begin
            {sl_a, sl_b} = i[1:0];
            #10;

            $display("Switch-level: a=%b, b=%b, sum=%b, carry=%b", sl_a, sl_b,
                     sl_sum, sl_carry);
        end

        $finish;
    end
endmodule

half_adder/wave.vcd
$date
	Fri Apr 10 15:16:22 2026
$end
$version
	Icarus Verilog
$end
$timescale
	1s
$end
$scope module half_adder_tb $end
$var wire 1 ! sl_carry $end
$var wire 1 " sl_sum $end
$var wire 1 # gl_sum $end
$var wire 1 $ gl_carry $end
$var wire 1 % df_sum $end
$var wire 1 & df_carry $end
$var wire 1 ' bh_sum $end
$var wire 1 ( bh_carry $end
$var reg 1 ) bh_a $end
$var reg 1 * bh_b $end
$var reg 1 + df_a $end
$var reg 1 , df_b $end
$var reg 1 - gl_a $end
$var reg 1 . gl_b $end
$var reg 1 / sl_a $end
$var reg 1 0 sl_b $end
$scope module bh $end
$var wire 1 ) a $end
$var wire 1 * b $end
$var reg 1 ( carry $end
$var reg 1 ' sum $end
$upscope $end
$scope module df $end
$var wire 1 + a $end
$var wire 1 , b $end
$var wire 1 & carry $end
$var wire 1 % sum $end
$upscope $end
$scope module gl $end
$var wire 1 - a $end
$var wire 1 . b $end
$var wire 1 $ carry $end
$var wire 1 # sum $end
$upscope $end
$scope module sl $end
$var wire 1 / a $end
$var wire 1 0 b $end
$var wire 1 ! carry $end
$var wire 1 " sum $end
$scope module and_gate $end
$var wire 1 / a $end
$var wire 1 0 b $end
$var wire 1 1 nand_out $end
$var wire 1 ! out $end
$scope module nand1 $end
$var wire 1 / a $end
$var wire 1 0 b $end
$var wire 1 2 gnd $end
$var wire 1 1 out $end
$var wire 1 3 vcc $end
$var wire 1 4 w1 $end
$upscope $end
$scope module nand2 $end
$var wire 1 1 a $end
$var wire 1 1 b $end
$var wire 1 5 gnd $end
$var wire 1 ! out $end
$var wire 1 6 vcc $end
$var wire 1 7 w1 $end
$upscope $end
$upscope $end
$scope module xor_gate $end
$var wire 1 / a $end
$var wire 1 0 b $end
$var wire 1 8 nand1_out $end
$var wire 1 9 nand2_out $end
$var wire 1 : nand3_out $end
$var wire 1 " out $end
$scope module nand1 $end
$var wire 1 / a $end
$var wire 1 0 b $end
$var wire 1 ; gnd $end
$var wire 1 8 out $end
$var wire 1 < vcc $end
$var wire 1 = w1 $end
$upscope $end
$scope module nand2 $end
$var wire 1 / a $end
$var wire 1 8 b $end
$var wire 1 > gnd $end
$var wire 1 9 out $end
$var wire 1 ? vcc $end
$var wire 1 @ w1 $end
$upscope $end
$scope module nand3 $end
$var wire 1 8 a $end
$var wire 1 0 b $end
$var wire 1 A gnd $end
$var wire 1 : out $end
$var wire 1 B vcc $end
$var wire 1 C w1 $end
$upscope $end
$scope module nand4 $end
$var wire 1 9 a $end
$var wire 1 : b $end
$var wire 1 D gnd $end
$var wire 1 " out $end
$var wire 1 E vcc $end
$var wire 1 F w1 $end
$upscope $end
$upscope $end
$upscope $end
$scope begin $ivl_for_loop0 $end
$var integer 32 G i [31:0] $end
$upscope $end
$scope begin $ivl_for_loop1 $end
$var integer 32 H i [31:0] $end
$upscope $end
$scope begin $ivl_for_loop2 $end
$var integer 32 I i [31:0] $end
$upscope $end
$scope begin $ivl_for_loop3 $end
$var integer 32 J i [31:0] $end
$upscope $end
$upscope $end
$enddefinitions $end
$comment Show the parameter values. $end
$dumpall
$end
#0
$dumpvars
bx J
bx I
bx H
b0 G
xF
1E
0D
xC
1B
0A
x@
1?
0>
x=
1<
0;
x:
x9
x8
x7
16
05
x4
13
02
x1
x0
x/
x.
x-
0,
0+
x*
x)
x(
x'
0&
0%
x$
x#
x"
x!
$end
#10
1%
1,
b1 G
#20
1+
0,
b10 G
#30
0%
1&
1,
b11 G
#40
0(
0'
0)
0*
b0 H
b100 G
#50
1'
1*
b1 H
#60
1)
0*
b10 H
#70
1(
0'
1*
b11 H
#80
0#
0$
0-
0.
b0 I
b100 H
#90
1#
1.
b1 I
#100
1-
0.
b10 I
#110
0#
1$
1.
b11 I
#120
0"
19
0/
0!
07
11
z4
0@
18
z=
0F
1:
zC
00
b0 J
b100 I
#130
04
0=
1"
zF
0:
0C
10
b1 J
#140
09
1/
z4
z=
1"
0F
1:
zC
00
b10 J
#150
1!
z7
01
04
0"
19
z@
08
0=
0F
1:
0C
10
b11 J
#160
b100 J
