decoders/3x8/design.v
module decoder3x8 (
    input [2:0] in,
    output reg [7:0] out
);

    always @(*) begin
        case (in)
            3'b000:  out = 8'b00000001;
            3'b001:  out = 8'b00000010;
            3'b010:  out = 8'b00000100;
            3'b011:  out = 8'b00001000;
            3'b100:  out = 8'b00010000;
            3'b101:  out = 8'b00100000;
            3'b110:  out = 8'b01000000;
            3'b111:  out = 8'b10000000;
            default: out = 8'b00000000;
        endcase
    end

endmodule

full_adder_by_decoder/design.v
`include "/home/jack/struent_semiconductors_intern/decoders/3x8/design.v"

module full_adder_by_decoder (
    a,
    b,
    cin,
    sum,
    cout
);
    input a, b, cin;
    output sum, cout;
    wire [7:0] out;

    decoder3x8 decoder1 (
        .in ({a, b, cin}),
        .out(out)
    );

    assign sum  = out[1] | out[2] | out[4] | out[7];
    assign cout = out[3] | out[5] | out[6] | out[7];

endmodule

full_adder_by_decoder/testbench.v
module testbench;
    reg a, b, cin;
    wire sum, cout;

    full_adder_by_decoder uut (
        .a(a),
        .b(b),
        .cin(cin),
        .sum(sum),
        .cout(cout),
    );

    initial begin
        $dumpfile("wave.vcd");
        $dumpvars(0, testbench);

        for (integer i = 0; i < 8; i++) begin
            {a, b, cin} = i[2:0];
            #10;

            $display("a=%b, b=%b, cin=%b, sum=%b, carry=%b", a, b, cin, sum,
                     cout);
        end

        $finish;
    end
endmodule

full_adder_by_decoder/wave.vcd
$date
	Sun Apr 26 22:28:55 2026
$end
$version
	Icarus Verilog
$end
$timescale
	1s
$end
$scope module testbench $end
$var wire 1 ! sum $end
$var wire 1 " cout $end
$var reg 1 # a $end
$var reg 1 $ b $end
$var reg 1 % cin $end
$scope module uut $end
$var wire 1 # a $end
$var wire 1 $ b $end
$var wire 1 % cin $end
$var wire 1 " cout $end
$var wire 1 ! sum $end
$var wire 8 & out [7:0] $end
$scope module decoder1 $end
$var wire 3 ' in [2:0] $end
$var reg 8 ( out [7:0] $end
$upscope $end
$upscope $end
$scope begin $ivl_for_loop0 $end
$var integer 32 ) i [31:0] $end
$upscope $end
$upscope $end
$enddefinitions $end
$comment Show the parameter values. $end
$dumpall
$end
#0
$dumpvars
b0 )
b1 (
b0 '
b1 &
0%
0$
0#
0"
0!
$end
#10
1!
b10 &
b10 (
b1 '
1%
b1 )
#20
b100 &
b100 (
1$
b10 '
0%
b10 )
#30
1"
0!
b1000 &
b1000 (
b11 '
1%
b11 )
#40
0"
1!
b10000 &
b10000 (
1#
0$
b100 '
0%
b100 )
#50
1"
0!
b100000 &
b100000 (
b101 '
1%
b101 )
#60
b1000000 &
b1000000 (
1$
b110 '
0%
b110 )
#70
1!
b10000000 &
b10000000 (
b111 '
1%
b111 )
#80
b1000 )
