encoders/4x2/design.v
module encoder4x2 (
    input [3:0] in,
    output reg [1:0] out
);

    always @(*) begin
        case (in)
            4'b0001: out = 2'b00;
            4'b0010: out = 2'b01;
            4'b0100: out = 2'b10;
            4'b1000: out = 2'b11;
            default: out = 2'b00;
        endcase
    end
endmodule

encoders/4x2/testbench.v
module testbench;
    reg  [3:0] in;
    wire [1:0] out;

    encoder4x2 uut (
        .in (in),
        .out(out)
    );

    initial begin
        $dumpfile("wave.vcd");
        $dumpvars(0, testbench);

        $monitor("in = %b | out = %b", in, out);

        for (integer i = 0; i < 16; i++) begin
            in = i[3:0];
            #15;
        end

        $finish;
    end
endmodule

encoders/4x2/wave.vcd
$date
	Mon Apr 20 12:24:23 2026
$end
$version
	Icarus Verilog
$end
$timescale
	1s
$end
$scope module testbench $end
$var wire 2 ! out [1:0] $end
$var reg 4 " in [3:0] $end
$scope module uut $end
$var wire 4 # in [3:0] $end
$var reg 2 $ out [1:0] $end
$upscope $end
$scope begin $ivl_for_loop0 $end
$var integer 32 % i [31:0] $end
$upscope $end
$upscope $end
$enddefinitions $end
$comment Show the parameter values. $end
$dumpall
$end
#0
$dumpvars
b0 %
b0 $
b0 #
b0 "
b0 !
$end
#15
b1 "
b1 #
b1 %
#30
b1 !
b1 $
b10 "
b10 #
b10 %
#45
b0 !
b0 $
b11 "
b11 #
b11 %
#60
b10 !
b10 $
b100 "
b100 #
b100 %
#75
b0 !
b0 $
b101 "
b101 #
b101 %
#90
b110 "
b110 #
b110 %
#105
b111 "
b111 #
b111 %
#120
b11 !
b11 $
b1000 "
b1000 #
b1000 %
#135
b0 !
b0 $
b1001 "
b1001 #
b1001 %
#150
b1010 "
b1010 #
b1010 %
#165
b1011 "
b1011 #
b1011 %
#180
b1100 "
b1100 #
b1100 %
#195
b1101 "
b1101 #
b1101 %
#210
b1110 "
b1110 #
b1110 %
#225
b1111 "
b1111 #
b1111 %
#240
b10000 %
