demuxes/1x2/design.v
module demux1x2 (
    in,
    sel,
    out
);
    input in, sel;
    output [1:0] out;

    assign out[0] = in & ~sel;
    assign out[1] = in & sel;

endmodule

demuxes/1x4/design.v
`include "/home/jack/struent_semiconductors_intern/demuxes/1x2/design.v"

module demux1x4 (
    in,
    sel,
    out
);
    input in;
    input [1:0] sel;
    output [3:0] out;
    wire [1:0] out1;

    demux1x2 demux0 (
        .in (in),
        .sel(sel[1]),
        .out(out1)
    );

    demux1x2 demux1 (
        .in (out1[0]),
        .sel(sel[0]),
        .out(out[1:0])
    );

    demux1x2 demux2 (
        .in (out1[1]),
        .sel(sel[0]),
        .out(out[3:2])
    );

endmodule

demuxes/1x8/design.v
`include "/home/jack/struent_semiconductors_intern/demuxes/1x4/design.v"
`include "/home/jack/struent_semiconductors_intern/demuxes/1x2/design.v"

module demux1x8 (
    in,
    sel,
    out
);
    input in;
    input [2:0] sel;
    output [7:0] out;
    wire [1:0] out1;

    demux1x2 demux0 (
        .in (in),
        .sel(sel[2]),
        .out(out1)
    );

    demux1x4 demux1 (
        .in (out1[0]),
        .sel(sel[1:0]),
        .out(out[3:0])
    );

    demux1x4 demux2 (
        .in (out1[1]),
        .sel(sel[1:0]),
        .out(out[7:4])
    );

endmodule

demuxes/1x16/design.v
`include "/home/jack/struent_semiconductors_intern/demuxes/1x8/design.v"
`include "/home/jack/struent_semiconductors_intern/demuxes/1x2/design.v"

module demux1x16 (
    in,
    sel,
    out
);

    input in;
    input [3:0] sel;
    output [15:0] out;
    wire [3:0] out1;

    demux1x2 demux0 (
        .in (in),
        .sel(sel[3]),
        .out(out1)
    );

    demux1x8 demux1 (
        .in (out1[0]),
        .sel(sel[2:0]),
        .out(out[7:0])
    );

    demux1x8 demux2 (
        .in (out1[1]),
        .sel(sel[2:0]),
        .out(out[15:8])
    );

endmodule

demuxes/1x16/testbench.v
module testbench;
    reg in;
    reg [3:0] sel;
    wire [15:0] out;

    demux1x16 dut (
        .in (in),
        .sel(sel),
        .out(out)
    );

    initial begin
        $dumpfile("wave.vcd");
        $dumpvars(0, testbench);

        $monitor("in=%b, sel=%b, out=%b", in, sel, out);

        in = 1;

        for (integer i = 0; i < 16; i++) begin
            sel = i[3:0];
            #10;
        end

        $finish;
    end
endmodule

demuxes/1x16/wave.vcd
$date
	Mon Apr 13 12:50:22 2026
$end
$version
	Icarus Verilog
$end
$timescale
	1s
$end
$scope module testbench $end
$var wire 16 ! out [15:0] $end
$var reg 1 " in $end
$var reg 4 # sel [3:0] $end
$scope module dut $end
$var wire 1 " in $end
$var wire 4 $ sel [3:0] $end
$var wire 4 % out1 [3:0] $end
$var wire 16 & out [15:0] $end
$scope module demux0 $end
$var wire 1 " in $end
$var wire 1 ' sel $end
$var wire 2 ( out [1:0] $end
$upscope $end
$scope module demux1 $end
$var wire 1 ) in $end
$var wire 3 * sel [2:0] $end
$var wire 2 + out1 [1:0] $end
$var wire 8 , out [7:0] $end
$scope module demux0 $end
$var wire 1 ) in $end
$var wire 1 - sel $end
$var wire 2 . out [1:0] $end
$upscope $end
$scope module demux1 $end
$var wire 1 / in $end
$var wire 2 0 sel [1:0] $end
$var wire 2 1 out1 [1:0] $end
$var wire 4 2 out [3:0] $end
$scope module demux0 $end
$var wire 1 / in $end
$var wire 1 3 sel $end
$var wire 2 4 out [1:0] $end
$upscope $end
$scope module demux1 $end
$var wire 1 5 in $end
$var wire 1 6 sel $end
$var wire 2 7 out [1:0] $end
$upscope $end
$scope module demux2 $end
$var wire 1 8 in $end
$var wire 1 9 sel $end
$var wire 2 : out [1:0] $end
$upscope $end
$upscope $end
$scope module demux2 $end
$var wire 1 ; in $end
$var wire 2 < sel [1:0] $end
$var wire 2 = out1 [1:0] $end
$var wire 4 > out [3:0] $end
$scope module demux0 $end
$var wire 1 ; in $end
$var wire 1 ? sel $end
$var wire 2 @ out [1:0] $end
$upscope $end
$scope module demux1 $end
$var wire 1 A in $end
$var wire 1 B sel $end
$var wire 2 C out [1:0] $end
$upscope $end
$scope module demux2 $end
$var wire 1 D in $end
$var wire 1 E sel $end
$var wire 2 F out [1:0] $end
$upscope $end
$upscope $end
$upscope $end
$scope module demux2 $end
$var wire 1 G in $end
$var wire 3 H sel [2:0] $end
$var wire 2 I out1 [1:0] $end
$var wire 8 J out [7:0] $end
$scope module demux0 $end
$var wire 1 G in $end
$var wire 1 K sel $end
$var wire 2 L out [1:0] $end
$upscope $end
$scope module demux1 $end
$var wire 1 M in $end
$var wire 2 N sel [1:0] $end
$var wire 2 O out1 [1:0] $end
$var wire 4 P out [3:0] $end
$scope module demux0 $end
$var wire 1 M in $end
$var wire 1 Q sel $end
$var wire 2 R out [1:0] $end
$upscope $end
$scope module demux1 $end
$var wire 1 S in $end
$var wire 1 T sel $end
$var wire 2 U out [1:0] $end
$upscope $end
$scope module demux2 $end
$var wire 1 V in $end
$var wire 1 W sel $end
$var wire 2 X out [1:0] $end
$upscope $end
$upscope $end
$scope module demux2 $end
$var wire 1 Y in $end
$var wire 2 Z sel [1:0] $end
$var wire 2 [ out1 [1:0] $end
$var wire 4 \ out [3:0] $end
$scope module demux0 $end
$var wire 1 Y in $end
$var wire 1 ] sel $end
$var wire 2 ^ out [1:0] $end
$upscope $end
$scope module demux1 $end
$var wire 1 _ in $end
$var wire 1 ` sel $end
$var wire 2 a out [1:0] $end
$upscope $end
$scope module demux2 $end
$var wire 1 b in $end
$var wire 1 c sel $end
$var wire 2 d out [1:0] $end
$upscope $end
$upscope $end
$upscope $end
$upscope $end
$scope begin $ivl_for_loop0 $end
$var integer 32 e i [31:0] $end
$upscope $end
$upscope $end
$enddefinitions $end
$comment Show the parameter values. $end
$dumpall
$end
#0
$dumpvars
b0 e
b0 d
0c
0b
b0 a
0`
0_
b0 ^
0]
b0 \
b0 [
b0 Z
0Y
b0 X
0W
0V
b0 U
0T
0S
b0 R
0Q
b0 P
b0 O
b0 N
0M
b0 L
0K
b0 J
b0 I
b0 H
0G
b0 F
0E
0D
b0 C
0B
0A
b0 @
0?
b0 >
b0 =
b0 <
0;
b0 :
09
08
b1 7
06
15
b1 4
03
b1 2
b1 1
b0 0
1/
b1 .
0-
b1 ,
b1 +
b0 *
1)
b1 (
0'
b1 &
b1 %
b0 $
b0 #
1"
b1 !
$end
#10
b10 !
b10 &
b10 ,
b10 2
b10 7
16
19
1B
1E
1T
1W
1`
1c
b1 0
b1 <
b1 N
b1 Z
b1 *
b1 H
b1 #
b1 $
b1 e
#20
05
b1 :
18
b10 1
b10 4
b100 !
b100 &
b100 ,
b100 2
b0 7
13
06
09
1?
0B
0E
1Q
0T
0W
1]
0`
0c
b10 0
b10 <
b10 N
b10 Z
b10 *
b10 H
b10 #
b10 $
b10 e
#30
b1000 !
b1000 &
b1000 ,
b1000 2
b10 :
16
19
1B
1E
1T
1W
1`
1c
b11 0
b11 <
b11 N
b11 Z
b11 *
b11 H
b11 #
b11 $
b11 e
#40
b0 7
b1 >
b1 C
05
1A
0/
08
b1 =
b1 @
1;
b0 1
b0 4
b10000 !
b10000 &
b10000 ,
b0 2
b0 :
b10 +
b10 .
03
06
09
0?
0B
0E
0Q
0T
0W
0]
0`
0c
1-
b0 0
b0 <
1K
b0 N
b0 Z
b100 *
b100 H
b100 #
b100 $
b100 e
#50
b100000 !
b100000 &
b100000 ,
b10 >
b10 C
16
19
1B
1E
1T
1W
1`
1c
b1 0
b1 <
b1 N
b1 Z
b101 *
b101 H
b101 #
b101 $
b101 e
#60
0A
b1 F
1D
b10 =
b10 @
b1000000 !
b1000000 &
b1000000 ,
b100 >
b0 C
13
06
09
1?
0B
0E
1Q
0T
0W
1]
0`
0c
b10 0
b10 <
b10 N
b10 Z
b110 *
b110 H
b110 #
b110 $
b110 e
#70
b10000000 !
b10000000 &
b10000000 ,
b1000 >
b10 F
16
19
1B
1E
1T
1W
1`
1c
b11 0
b11 <
b11 N
b11 Z
b111 *
b111 H
b111 #
b111 $
b111 e
#80
b0 2
b0 7
b1 J
b1 P
b1 U
05
1S
b0 1
b0 4
b1 O
b1 R
0/
0D
1M
0)
0;
b0 =
b0 @
b100000000 !
b100000000 &
b0 ,
b0 >
b0 F
b1 I
b1 L
1G
b0 +
b0 .
03
06
09
0?
0B
0E
0Q
0T
0W
0]
0`
0c
b10 %
b10 (
0-
b0 0
b0 <
0K
b0 N
b0 Z
1'
b0 *
b0 H
b1000 #
b1000 $
b1000 e
#90
b1000000000 !
b1000000000 &
b10 J
b10 P
b10 U
16
19
1B
1E
1T
1W
1`
1c
b1 0
b1 <
b1 N
b1 Z
b1 *
b1 H
b1001 #
b1001 $
b1001 e
#100
0S
b1 X
1V
b10 O
b10 R
b10000000000 !
b10000000000 &
b100 J
b100 P
b0 U
13
06
09
1?
0B
0E
1Q
0T
0W
1]
0`
0c
b10 0
b10 <
b10 N
b10 Z
b10 *
b10 H
b1010 #
b1010 $
b1010 e
#110
b100000000000 !
b100000000000 &
b1000 J
b1000 P
b10 X
16
19
1B
1E
1T
1W
1`
1c
b11 0
b11 <
b11 N
b11 Z
b11 *
b11 H
b1011 #
b1011 $
b1011 e
#120
b0 U
b1 \
b1 a
0S
1_
0M
0V
b1 [
b1 ^
1Y
b0 O
b0 R
b1000000000000 !
b1000000000000 &
b10000 J
b0 P
b0 X
03
06
09
0?
0B
0E
b10 I
b10 L
0Q
0T
0W
0]
0`
0c
1-
b0 0
b0 <
1K
b0 N
b0 Z
b100 *
b100 H
b1100 #
b1100 $
b1100 e
#130
b10000000000000 !
b10000000000000 &
b100000 J
b10 \
b10 a
16
19
1B
1E
1T
1W
1`
1c
b1 0
b1 <
b1 N
b1 Z
b101 *
b101 H
b1101 #
b1101 $
b1101 e
#140
0_
b1 d
1b
b10 [
b10 ^
b100000000000000 !
b100000000000000 &
b1000000 J
b100 \
b0 a
13
06
09
1?
0B
0E
1Q
0T
0W
1]
0`
0c
b10 0
b10 <
b10 N
b10 Z
b110 *
b110 H
b1110 #
b1110 $
b1110 e
#150
b1000000000000000 !
b1000000000000000 &
b10000000 J
b1000 \
b10 d
16
19
1B
1E
1T
1W
1`
1c
b11 0
b11 <
b11 N
b11 Z
b111 *
b111 H
b1111 #
b1111 $
b1111 e
#160
b10000 e
