encoders/8x3/design.v
module encoder8x3 (
    input [7:0] in,
    output reg [2:0] out
);

    always @(*) begin
        case (in)
            8'b00000001: out = 3'd0;
            8'b00000010: out = 3'd1;
            8'b00000100: out = 3'd2;
            8'b00001000: out = 3'd3;
            8'b00010000: out = 3'd4;
            8'b00100000: out = 3'd5;
            8'b01000000: out = 3'd6;
            8'b10000000: out = 3'd7;
            default: out = 3'd0;
        endcase
    end

endmodule

encoders/8x3/testbench.v
module testbench;
    reg  [7:0] in;
    wire [2:0] out;

    encoder8x3 uut (
        .in (in),
        .out(out)
    );

    initial begin
        $dumpfile("wave.vcd");
        $dumpvars(0, testbench);

        $monitor("in = %b | out = %b", in, out);

        for (integer i = 0; i < 64; i++) begin
            in = i[7:0];
            #15;
        end

        $finish;
    end
endmodule

encoders/8x3/wave.vcd
$date
	Mon Apr 20 12:21:20 2026
$end
$version
	Icarus Verilog
$end
$timescale
	1s
$end
$scope module testbench $end
$var wire 3 ! out [2:0] $end
$var reg 8 " in [7:0] $end
$scope module uut $end
$var wire 8 # in [7:0] $end
$var reg 3 $ out [2:0] $end
$upscope $end
$scope begin $ivl_for_loop0 $end
$var integer 32 % i [31:0] $end
$upscope $end
$upscope $end
$enddefinitions $end
$comment Show the parameter values. $end
$dumpall
$end
#0
$dumpvars
b0 %
bx $
b0 #
b0 "
bx !
$end
#15
b0 !
b0 $
b1 "
b1 #
b1 %
#30
b1 !
b1 $
b10 "
b10 #
b10 %
#45
bx !
bx $
b11 "
b11 #
b11 %
#60
b10 !
b10 $
b100 "
b100 #
b100 %
#75
bx !
bx $
b101 "
b101 #
b101 %
#90
b110 "
b110 #
b110 %
#105
b111 "
b111 #
b111 %
#120
b11 !
b11 $
b1000 "
b1000 #
b1000 %
#135
bx !
bx $
b1001 "
b1001 #
b1001 %
#150
b1010 "
b1010 #
b1010 %
#165
b1011 "
b1011 #
b1011 %
#180
b1100 "
b1100 #
b1100 %
#195
b1101 "
b1101 #
b1101 %
#210
b1110 "
b1110 #
b1110 %
#225
b1111 "
b1111 #
b1111 %
#240
b100 !
b100 $
b10000 "
b10000 #
b10000 %
#255
bx !
bx $
b10001 "
b10001 #
b10001 %
#270
b10010 "
b10010 #
b10010 %
#285
b10011 "
b10011 #
b10011 %
#300
b10100 "
b10100 #
b10100 %
#315
b10101 "
b10101 #
b10101 %
#330
b10110 "
b10110 #
b10110 %
#345
b10111 "
b10111 #
b10111 %
#360
b11000 "
b11000 #
b11000 %
#375
b11001 "
b11001 #
b11001 %
#390
b11010 "
b11010 #
b11010 %
#405
b11011 "
b11011 #
b11011 %
#420
b11100 "
b11100 #
b11100 %
#435
b11101 "
b11101 #
b11101 %
#450
b11110 "
b11110 #
b11110 %
#465
b11111 "
b11111 #
b11111 %
#480
b101 !
b101 $
b100000 "
b100000 #
b100000 %
#495
bx !
bx $
b100001 "
b100001 #
b100001 %
#510
b100010 "
b100010 #
b100010 %
#525
b100011 "
b100011 #
b100011 %
#540
b100100 "
b100100 #
b100100 %
#555
b100101 "
b100101 #
b100101 %
#570
b100110 "
b100110 #
b100110 %
#585
b100111 "
b100111 #
b100111 %
#600
b101000 "
b101000 #
b101000 %
#615
b101001 "
b101001 #
b101001 %
#630
b101010 "
b101010 #
b101010 %
#645
b101011 "
b101011 #
b101011 %
#660
b101100 "
b101100 #
b101100 %
#675
b101101 "
b101101 #
b101101 %
#690
b101110 "
b101110 #
b101110 %
#705
b101111 "
b101111 #
b101111 %
#720
b110000 "
b110000 #
b110000 %
#735
b110001 "
b110001 #
b110001 %
#750
b110010 "
b110010 #
b110010 %
#765
b110011 "
b110011 #
b110011 %
#780
b110100 "
b110100 #
b110100 %
#795
b110101 "
b110101 #
b110101 %
#810
b110110 "
b110110 #
b110110 %
#825
b110111 "
b110111 #
b110111 %
#840
b111000 "
b111000 #
b111000 %
#855
b111001 "
b111001 #
b111001 %
#870
b111010 "
b111010 #
b111010 %
#885
b111011 "
b111011 #
b111011 %
#900
b111100 "
b111100 #
b111100 %
#915
b111101 "
b111101 #
b111101 %
#930
b111110 "
b111110 #
b111110 %
#945
b111111 "
b111111 #
b111111 %
#960
b1000000 %
