universal_gates/nand/design.v
// Design of a NAND gate using PMOS and NMOS transistors
module nand_gate(
    a,
    b,
    out
);
    input a,b;
    output out;

    supply1 vcc;
    supply0 gnd;

    wire w1;

    pmos p1(out, vcc, a);
    pmos p2(out, vcc, b);

    nmos n1(out, w1, a);
    nmos n2(w1, gnd, b);

endmodule

gates_by_universal_gates/xor/design.v
`include "/home/jack/struent_semiconductors_intern/universal_gates/nor/design.v"
`include "/home/jack/struent_semiconductors_intern/universal_gates/nand/design.v"


// XOR gate implemented using NAND gates
module xor_by_nand (
    a,
    b,
    out
);

    input a, b;
    output out;

    wire nand1_out;
    wire nand2_out;
    wire nand3_out;

    nand_gate nand1(.a(a), .b(b), .out(nand1_out));
    nand_gate nand2(.a(a), .b(nand1_out), .out(nand2_out));
    nand_gate nand3(.a(nand1_out), .b(b), .out(nand3_out));
    nand_gate nand4(.a(nand2_out), .b(nand3_out), .out(out));

endmodule


// XOR gate implemented using NOR gates
module xor_by_nor (
    a,
    b,
    out
);
    
    input a, b;
    output out;

    wire nor1_out;
    wire nor2_out;
    wire nor3_out;
    wire nor4_out;

    nor_gate nor1(.a(a), .b(b), .out(nor1_out));
    nor_gate nor2(.a(a), .b(nor1_out), .out(nor2_out));
    nor_gate nor3(.a(nor1_out), .b(b), .out(nor3_out));
    nor_gate nor4(.a(nor2_out), .b(nor3_out), .out(nor4_out));
    nor_gate nor5(.a(nor4_out), .b(nor4_out), .out(out));

endmodule

gates_by_universal_gates/and/design.v
`include "/home/jack/struent_semiconductors_intern/universal_gates/nor/design.v"
`include "/home/jack/struent_semiconductors_intern/universal_gates/nand/design.v"

// AND gate implemented using NAND gates
module and_by_nand (
    a,
    b,
    out
);

    input a, b;
    output out;
    wire nand_out;

    nand_gate nand1 (
        .a  (a),
        .b  (b),
        .out(nand_out)
    );

    nand_gate nand2 (
        .a  (nand_out),
        .b  (nand_out),
        .out(out)
    );

endmodule


// AND gate implemented using NOR gates
module and_by_nor(
    a,
    b,
    out
);

    input a, b;
    output out;
    wire nor1_out;
    wire nor2_out;

    nor_gate nor1 (
        .a  (a),
        .b  (a),
        .out(nor1_out)
    );

    nor_gate nor2 (
        .a  (b),
        .b  (b),
        .out(nor2_out)
    );

    nor_gate nor3 (
        .a  (nor1_out),
        .b  (nor2_out),
        .out(out)
    );

endmodule

half_subtractor/design.v
`include "../gates_by_universal_gates/and/design.v"
`include "../gates_by_universal_gates/xor/design.v"

// Design of a half subtractor using data flow modeling
module half_subtractor_dataflow (
    a,
    b,
    diff,
    borrow
);

    input a, b;
    output diff, borrow;

    assign diff   = a ^ b;
    assign borrow = ~a & b;
endmodule

// Design of a half subtractor using behavioural modeling
module half_subtractor_behavioural (
    a,
    b,
    diff,
    borrow

);

    input a, b;
    output reg diff, borrow;

    always @(*) begin
        diff   = a ^ b;
        borrow = ~a & b;
    end

endmodule

// Design of a half subtractor using structural modeling
module half_subtractor_structural (
    a,
    b,
    diff,
    borrow
);

    input a, b;
    output diff, borrow;

    xor (diff, a, b);
    and (borrow, ~a, b);

endmodule

// Design of a half subtractor using switch level modeling
module half_subtractor_switch_level (
    a,
    b,
    diff,
    borrow
);

    input a, b;
    output diff, borrow;

    and_by_nand and_gate (
        .a  (~a),
        .b  (b),
        .out(borrow)
    );

    xor_by_nand xor_gate (
        .a  (a),
        .b  (b),
        .out(diff)
    );

endmodule

half_subtractor/testbench.v
module half_subtractor_tb;
    reg df_a, df_b;
    wire df_diff, df_borrow;

    reg bh_a, bh_b;
    wire bh_diff, bh_borrow;

    reg gl_a, gl_b;
    wire gl_diff, gl_borrow;

    reg sl_a, sl_b;
    wire sl_diff, sl_borrow;

    half_subtractor_dataflow df (
        .a(df_a),
        .b(df_b),
        .diff(df_diff),
        .borrow(df_borrow)
    );

    half_subtractor_behavioural bh (
        .a(bh_a),
        .b(bh_b),
        .diff(bh_diff),
        .borrow(bh_borrow)
    );

    half_subtractor_structural gl (
        .a(gl_a),
        .b(gl_b),
        .diff(gl_diff),
        .borrow(gl_borrow)
    );

    half_subtractor_switch_level sl (
        .a(sl_a),
        .b(sl_b),
        .diff(sl_diff),
        .borrow(sl_borrow)
    );

    initial begin
        $dumpfile("wave.vcd");
        $dumpvars(0, half_subtractor_tb);

        for (integer i = 0; i < 4; i++) begin
            {df_a, df_b} = i[1:0];
            #10;

            $display("Dataflow: a=%b, b=%b, diff=%b, borrow=%b", df_a, df_b,
                     df_diff, df_borrow);
        end

        $write("\n");

        for (integer i = 0; i < 4; i++) begin
            {bh_a, bh_b} = i[1:0];
            #10;

            $display("Behavioural: a=%b, b=%b, diff=%b, borrow=%b", bh_a, bh_b,
                     bh_diff, bh_borrow);
        end

        $write("\n");

        for (integer i = 0; i < 4; i++) begin
            {gl_a, gl_b} = i[1:0];
            #10;

            $display("Gate-level: a=%b, b=%b, diff=%b, borrow=%b", gl_a, gl_b,
                     gl_diff, gl_borrow);
        end
        
        $write("\n");

        for (integer i = 0; i < 4; i++) begin
            {sl_a, sl_b} = i[1:0];
            #10;

            $display("Switch-level: a=%b, b=%b, diff=%b, borrow=%b", sl_a, sl_b,
                     sl_diff, sl_borrow);
        end

        $finish;
    end
endmodule

half_subtractor/wave.vcd
$date
	Fri Apr 10 15:16:46 2026
$end
$version
	Icarus Verilog
$end
$timescale
	1s
$end
$scope module half_subtractor_tb $end
$var wire 1 ! sl_borrow $end
$var wire 1 " sl_diff $end
$var wire 1 # gl_diff $end
$var wire 1 $ gl_borrow $end
$var wire 1 % df_diff $end
$var wire 1 & df_borrow $end
$var wire 1 ' bh_diff $end
$var wire 1 ( bh_borrow $end
$var reg 1 ) bh_a $end
$var reg 1 * bh_b $end
$var reg 1 + df_a $end
$var reg 1 , df_b $end
$var reg 1 - gl_a $end
$var reg 1 . gl_b $end
$var reg 1 / sl_a $end
$var reg 1 0 sl_b $end
$scope module bh $end
$var wire 1 ) a $end
$var wire 1 * b $end
$var reg 1 ( borrow $end
$var reg 1 ' diff $end
$upscope $end
$scope module df $end
$var wire 1 + a $end
$var wire 1 , b $end
$var wire 1 & borrow $end
$var wire 1 % diff $end
$upscope $end
$scope module gl $end
$var wire 1 - a $end
$var wire 1 . b $end
$var wire 1 $ borrow $end
$var wire 1 # diff $end
$upscope $end
$scope module sl $end
$var wire 1 / a $end
$var wire 1 0 b $end
$var wire 1 ! borrow $end
$var wire 1 " diff $end
$scope module and_gate $end
$var wire 1 1 a $end
$var wire 1 0 b $end
$var wire 1 2 nand_out $end
$var wire 1 ! out $end
$scope module nand1 $end
$var wire 1 1 a $end
$var wire 1 0 b $end
$var wire 1 3 gnd $end
$var wire 1 2 out $end
$var wire 1 4 vcc $end
$var wire 1 5 w1 $end
$upscope $end
$scope module nand2 $end
$var wire 1 2 a $end
$var wire 1 2 b $end
$var wire 1 6 gnd $end
$var wire 1 ! out $end
$var wire 1 7 vcc $end
$var wire 1 8 w1 $end
$upscope $end
$upscope $end
$scope module xor_gate $end
$var wire 1 / a $end
$var wire 1 0 b $end
$var wire 1 9 nand1_out $end
$var wire 1 : nand2_out $end
$var wire 1 ; nand3_out $end
$var wire 1 " out $end
$scope module nand1 $end
$var wire 1 / a $end
$var wire 1 0 b $end
$var wire 1 < gnd $end
$var wire 1 9 out $end
$var wire 1 = vcc $end
$var wire 1 > w1 $end
$upscope $end
$scope module nand2 $end
$var wire 1 / a $end
$var wire 1 9 b $end
$var wire 1 ? gnd $end
$var wire 1 : out $end
$var wire 1 @ vcc $end
$var wire 1 A w1 $end
$upscope $end
$scope module nand3 $end
$var wire 1 9 a $end
$var wire 1 0 b $end
$var wire 1 B gnd $end
$var wire 1 ; out $end
$var wire 1 C vcc $end
$var wire 1 D w1 $end
$upscope $end
$scope module nand4 $end
$var wire 1 : a $end
$var wire 1 ; b $end
$var wire 1 E gnd $end
$var wire 1 " out $end
$var wire 1 F vcc $end
$var wire 1 G w1 $end
$upscope $end
$upscope $end
$upscope $end
$scope begin $ivl_for_loop0 $end
$var integer 32 H i [31:0] $end
$upscope $end
$scope begin $ivl_for_loop1 $end
$var integer 32 I i [31:0] $end
$upscope $end
$scope begin $ivl_for_loop2 $end
$var integer 32 J i [31:0] $end
$upscope $end
$scope begin $ivl_for_loop3 $end
$var integer 32 K i [31:0] $end
$upscope $end
$upscope $end
$enddefinitions $end
$comment Show the parameter values. $end
$dumpall
$end
#0
$dumpvars
bx K
bx J
bx I
b0 H
xG
1F
0E
xD
1C
0B
xA
1@
0?
x>
1=
0<
x;
x:
x9
x8
17
06
x5
14
03
x2
x1
x0
x/
x.
x-
0,
0+
x*
x)
x(
x'
0&
0%
x$
x#
x"
x!
$end
#10
1%
1&
1,
b1 H
#20
0&
1+
0,
b10 H
#30
0%
1,
b11 H
#40
0(
0'
0)
0*
b0 I
b100 H
#50
1(
1'
1*
b1 I
#60
0(
1)
0*
b10 I
#70
0'
1*
b11 I
#80
0#
0$
0-
0.
b0 J
b100 I
#90
1#
1$
1.
b1 J
#100
0$
1-
0.
b10 J
#110
0#
1.
b11 J
#120
11
0"
1:
0/
0!
08
12
z5
0A
19
z>
0G
1;
zD
00
b0 K
b100 J
#130
1!
z8
02
05
0>
1"
zG
0;
0D
10
b1 K
#140
01
0:
1/
0!
08
12
z5
z>
1"
0G
1;
zD
00
b10 K
#150
05
0"
1:
zA
09
0>
0G
1;
0D
10
b11 K
#160
b100 K
