hexadecimal_to_binary/design.v
module hexadecimal_to_binary (
    input [15:0] in,
    output reg [3:0] out
);

    always @(*) begin
        out = 4'd0;

        out[3] = in[8] | in[9] | in[10] | in[11] | in[12] | in[13] | in[14] | in[15];

        out[2] = in[4] | in[5] | in[6] | in[7] | in[12] | in[13] | in[14] | in[15];

        out[1] = in[2] | in[3] | in[6] | in[7] | in[10] | in[11] | in[14] | in[15];

        out[0] = in[1] | in[3] | in[5] | in[7] | in[9] | in[11] | in[13] | in[15];

    end

endmodule

hexadecimal_to_binary/testbench.v
module testbench;
    reg [15:0] in;
    wire [3:0] out;
    integer i;

    hexadecimal_to_binary uut (
        .in (in),
        .out(out)
    );

    initial begin
        $dumpfile("wave.vcd");
        $dumpvars(0, testbench);

        for (i = 0; i < 16; i++) begin
            in = 16'd0;
            in[i] = 1;

            #15;
            $display("in = %b or %d | out = %b", in, i[3:0], out);
        end

        $finish;
    end

endmodule

hexadecimal_to_binary/wave.vcd
$date
	Wed Apr 22 15:35:57 2026
$end
$version
	Icarus Verilog
$end
$timescale
	1s
$end
$scope module testbench $end
$var wire 4 ! out [3:0] $end
$var reg 16 " in [15:0] $end
$var integer 32 # i [31:0] $end
$scope module uut $end
$var wire 16 $ in [15:0] $end
$var reg 4 % out [3:0] $end
$upscope $end
$upscope $end
$enddefinitions $end
$comment Show the parameter values. $end
$dumpall
$end
#0
$dumpvars
b0 %
b1 $
b0 #
b1 "
b0 !
$end
#15
b1 !
b1 %
b10 "
b10 $
b1 #
#30
b10 !
b10 %
b100 "
b100 $
b10 #
#45
b11 !
b11 %
b1000 "
b1000 $
b11 #
#60
b100 !
b100 %
b10000 "
b10000 $
b100 #
#75
b101 !
b101 %
b100000 "
b100000 $
b101 #
#90
b110 !
b110 %
b1000000 "
b1000000 $
b110 #
#105
b111 !
b111 %
b10000000 "
b10000000 $
b111 #
#120
b1000 !
b1000 %
b100000000 "
b100000000 $
b1000 #
#135
b1001 !
b1001 %
b1000000000 "
b1000000000 $
b1001 #
#150
b1010 !
b1010 %
b10000000000 "
b10000000000 $
b1010 #
#165
b1011 !
b1011 %
b100000000000 "
b100000000000 $
b1011 #
#180
b1100 !
b1100 %
b1000000000000 "
b1000000000000 $
b1100 #
#195
b1101 !
b1101 %
b10000000000000 "
b10000000000000 $
b1101 #
#210
b1110 !
b1110 %
b100000000000000 "
b100000000000000 $
b1110 #
#225
b1111 !
b1111 %
b1000000000000000 "
b1000000000000000 $
b1111 #
#240
b10000 #
