encoders/priority_encoders/4x2/design.v
module priority_encoder4x2_LSB (
    input [3:0] in,
    output reg [1:0] out
);

    always @(*) begin
        out = 2'd0;

        for (integer i = 0; i < 4; i++) begin
            if (in[i] && (in != 0) && (in & (in - 1)) == 0) out = i[3:0];
        end

    end

endmodule


module priority_encoder4x2_MSB (
    input [3:0] in,
    output reg [1:0] out
);

    always @(*) begin
        out = 2'd0;

        for (integer i = 3; i >= 0; i--) begin
            if (in[i] && (in != 0) && (in & (in - 1)) == 0) out = i[3:0];
        end

    end

endmodule

encoders/priority_encoders/4x2/testbench.v
module testbench;

    reg  [3:0] lsb_in;
    wire [1:0] lsb_out;

    reg  [3:0] msb_in;
    wire [1:0] msb_out;

    priority_encoder4x2_LSB uut (
        .in (lsb_in),
        .out(lsb_out)
    );

    priority_encoder4x2_MSB uut2 (
        .in (msb_in),
        .out(msb_out)
    );

    initial begin
        $dumpfile("wave.vcd");
        $dumpvars(0, testbench);

        for (integer i = 0; i < 16; i++) begin
            lsb_in = i[3:0];
            #15;
            $display("LSB: in = %b | out = %b", lsb_in, lsb_out);

        end

        $write("\n");

        for (integer i = 0; i < 16; i++) begin
            msb_in = i[3:0];
            #15;
            $display("MSB: in = %b | out = %b", msb_in, msb_out);
        end

        $finish;
    end
endmodule

encoders/priority_encoders/4x2/wave.vcd
$date
	Wed Apr 22 11:15:00 2026
$end
$version
	Icarus Verilog
$end
$timescale
	1s
$end
$scope module testbench $end
$var wire 2 ! msb_out [1:0] $end
$var wire 2 " lsb_out [1:0] $end
$var reg 4 # lsb_in [3:0] $end
$var reg 4 $ msb_in [3:0] $end
$scope module uut $end
$var wire 4 % in [3:0] $end
$var reg 2 & out [1:0] $end
$scope begin $ivl_for_loop0 $end
$var integer 32 ' i [31:0] $end
$upscope $end
$upscope $end
$scope module uut2 $end
$var wire 4 ( in [3:0] $end
$var reg 2 ) out [1:0] $end
$scope begin $ivl_for_loop1 $end
$var integer 32 * i [31:0] $end
$upscope $end
$upscope $end
$scope begin $ivl_for_loop2 $end
$var integer 32 + i [31:0] $end
$upscope $end
$scope begin $ivl_for_loop3 $end
$var integer 32 , i [31:0] $end
$upscope $end
$upscope $end
$enddefinitions $end
$comment Show the parameter values. $end
$dumpall
$end
#0
$dumpvars
bx ,
b0 +
bx *
bx )
bx (
b100 '
b0 &
b0 %
bx $
b0 #
b0 "
bx !
$end
#15
b100 '
b1 #
b1 %
b1 +
#30
b1 "
b1 &
b100 '
b10 #
b10 %
b10 +
#45
b100 '
b0 "
b0 &
b11 #
b11 %
b11 +
#60
b10 "
b10 &
b100 '
b100 #
b100 %
b100 +
#75
b100 '
b0 "
b0 &
b101 #
b101 %
b101 +
#90
b100 '
b110 #
b110 %
b110 +
#105
b100 '
b111 #
b111 %
b111 +
#120
b11 "
b11 &
b100 '
b1000 #
b1000 %
b1000 +
#135
b100 '
b0 "
b0 &
b1001 #
b1001 %
b1001 +
#150
b100 '
b1010 #
b1010 %
b1010 +
#165
b100 '
b1011 #
b1011 %
b1011 +
#180
b100 '
b1100 #
b1100 %
b1100 +
#195
b100 '
b1101 #
b1101 %
b1101 +
#210
b100 '
b1110 #
b1110 %
b1110 +
#225
b100 '
b1111 #
b1111 %
b1111 +
#240
b11111111111111111111111111111111 *
b0 !
b0 )
b0 $
b0 (
b0 ,
b10000 +
#255
b11111111111111111111111111111111 *
b1 $
b1 (
b1 ,
#270
b1 !
b1 )
b11111111111111111111111111111111 *
b10 $
b10 (
b10 ,
#285
b11111111111111111111111111111111 *
b0 !
b0 )
b11 $
b11 (
b11 ,
#300
b10 !
b10 )
b11111111111111111111111111111111 *
b100 $
b100 (
b100 ,
#315
b11111111111111111111111111111111 *
b0 !
b0 )
b101 $
b101 (
b101 ,
#330
b11111111111111111111111111111111 *
b110 $
b110 (
b110 ,
#345
b11111111111111111111111111111111 *
b111 $
b111 (
b111 ,
#360
b11 !
b11 )
b11111111111111111111111111111111 *
b1000 $
b1000 (
b1000 ,
#375
b11111111111111111111111111111111 *
b0 !
b0 )
b1001 $
b1001 (
b1001 ,
#390
b11111111111111111111111111111111 *
b1010 $
b1010 (
b1010 ,
#405
b11111111111111111111111111111111 *
b1011 $
b1011 (
b1011 ,
#420
b11111111111111111111111111111111 *
b1100 $
b1100 (
b1100 ,
#435
b11111111111111111111111111111111 *
b1101 $
b1101 (
b1101 ,
#450
b11111111111111111111111111111111 *
b1110 $
b1110 (
b1110 ,
#465
b11111111111111111111111111111111 *
b1111 $
b1111 (
b1111 ,
#480
b10000 ,
