universal_gates/nor/design.v
`ifndef UNIVERSAL_GATES_NOR_DESIGN_V
`define UNIVERSAL_GATES_NOR_DESIGN_V

// Design of a NOR gate using PMOS and NMOS transistors
module nor_gate (
    a,
    b,
    out
);

    input a, b;
    output out;

    supply1 vcc;
    supply0 gnd;

    wire w1;

    pmos p1 (w1, vcc, a);
    pmos p2 (out, w1, b);

    nmos n1 (out, gnd, a);
    nmos n2 (out, gnd, b);

endmodule

`endif

gates_by_universal_gates/or/design.v
`include "../../universal_gates/nand/design.v"
`include "../../universal_gates/nor/design.v"

// OR gate implemented using Nor gates
module or_by_nor (
    a,
    b,
    out
);

    input a, b;
    output out;
    wire nor_out;

    nor_gate nor1 (
        .a  (a),
        .b  (b),
        .out(nor_out)
    );

    nor_gate nor2 (
        .a  (nor_out),
        .b  (nor_out),
        .out(out)
    );

endmodule


// OR gate implemented using NAND gates
module or_by_nand(
    a,
    b,
    out
);

    input a, b;
    output out;
    wire nand1_out;
    wire nand2_out;

    nand_gate nand1 (
        .a  (a),
        .b  (a),
        .out(nand1_out)
    );

    nand_gate nand2 (
        .a  (b),
        .b  (b),
        .out(nand2_out)
    );

    nand_gate nand3 (
        .a  (nand1_out),
        .b  (nand2_out),
        .out(out)
    );

endmodule

gates_by_universal_gates/and/design.v
`include "/home/jack/struent_semiconductors_intern/universal_gates/nor/design.v"
`include "/home/jack/struent_semiconductors_intern/universal_gates/nand/design.v"

// AND gate implemented using NAND gates
module and_by_nand (
    a,
    b,
    out
);

    input a, b;
    output out;
    wire nand_out;

    nand_gate nand1 (
        .a  (a),
        .b  (b),
        .out(nand_out)
    );

    nand_gate nand2 (
        .a  (nand_out),
        .b  (nand_out),
        .out(out)
    );

endmodule


// AND gate implemented using NOR gates
module and_by_nor(
    a,
    b,
    out
);

    input a, b;
    output out;
    wire nor1_out;
    wire nor2_out;

    nor_gate nor1 (
        .a  (a),
        .b  (a),
        .out(nor1_out)
    );

    nor_gate nor2 (
        .a  (b),
        .b  (b),
        .out(nor2_out)
    );

    nor_gate nor3 (
        .a  (nor1_out),
        .b  (nor2_out),
        .out(out)
    );

endmodule

universal_gates/nand/design.v
`ifndef UNIVERSAL_GATES_NAND_DESIGN_V
`define UNIVERSAL_GATES_NAND_DESIGN_V

// Design of a NAND gate using PMOS and NMOS transistors
module nand_gate (
    a,
    b,
    out
);
    input a, b;
    output out;

    supply1 vcc;
    supply0 gnd;

    wire w1;

    pmos p1 (out, vcc, a);
    pmos p2 (out, vcc, b);

    nmos n1 (out, w1, a);
    nmos n2 (w1, gnd, b);

endmodule

`endif

different_modeling/half_adder/design.v
`include "../../gates_by_universal_gates/and/design.v"
`include "../../gates_by_universal_gates/or/design.v"

// Dataflow modeling
module half_adder_dataflow (
    a,
    b,
    sum,
    carry
);
    input a;
    input b;
    output sum;
    output carry;

    assign sum   = a ^ b;
    assign carry = a & b;

endmodule

// Behavioral modeling
module half_adder_behavioural (
    a,
    b,
    sum,
    carry
);
    input a;
    input b;
    output reg sum;
    output reg carry;

    always @(*) begin
        sum   = a ^ b;
        carry = a & b;
    end

endmodule


// Structural modeling
module half_adder_gate_level (
    a,
    b,
    sum,
    carry
);
    input a;
    input b;
    output sum;
    output carry;

    xor (sum, a, b);
    and (carry, a, b);

endmodule

// Switch-level modeling
module half_adder_switch_level (
    a,
    b,
    sum,
    carry
);
    input a;
    input b;
    output sum;
    output carry;

    wire and_gate2_out;
    wire and_gate3_out;

    and_by_nand and_gate (
        .a  (a),
        .b  (b),
        .out(carry)
    );

    and_by_nor and_gate2 (
        .a  (a),
        .b  (~b),
        .out(and_gate2_out)
    );

    and_by_nor and_gate3 (
        .a  (~a),
        .b  (b),
        .out(and_gate3_out)
    );

    or_by_nor or_gate (
        .a  (and_gate2_out),
        .b  (and_gate3_out),
        .out(sum)
    );

endmodule

different_modeling/half_adder/testbench.v
module half_adder_tb;
    reg df_a, df_b;
    wire df_sum, df_carry;

    reg bh_a, bh_b;
    wire bh_sum, bh_carry;

    reg gl_a, gl_b;
    wire gl_sum, gl_carry;

    reg sl_a, sl_b;
    wire sl_sum, sl_carry;

    half_adder_dataflow df (
        .a(df_a),
        .b(df_b),
        .sum(df_sum),
        .carry(df_carry)
    );

    half_adder_behavioural bh (
        .a(bh_a),
        .b(bh_b),
        .sum(bh_sum),
        .carry(bh_carry)
    );

    half_adder_gate_level gl (
        .a(gl_a),
        .b(gl_b),
        .sum(gl_sum),
        .carry(gl_carry)
    );

    half_adder_switch_level sl (
        .a(sl_a),
        .b(sl_b),
        .sum(sl_sum),
        .carry(sl_carry)
    );

    initial begin
        $dumpfile("wave.vcd");
        $dumpvars(0, half_adder_tb);

        for (integer i = 0; i < 4; i++) begin
            {df_a, df_b} = i[1:0];
            #10;

            $display("Dataflow: a=%b, b=%b, sum=%b, carry=%b", df_a, df_b,
                     df_sum, df_carry);
        end

        for (integer i = 0; i < 4; i++) begin
            {bh_a, bh_b} = i[1:0];
            #10;

            $display("Behavioural: a=%b, b=%b, sum=%b, carry=%b", bh_a, bh_b,
                     bh_sum, bh_carry);
        end

        for (integer i = 0; i < 4; i++) begin
            {gl_a, gl_b} = i[1:0];
            #10;

            $display("Gate-level: a=%b, b=%b, sum=%b, carry=%b", gl_a, gl_b,
                     gl_sum, gl_carry);
        end

        for (integer i = 0; i < 4; i++) begin
            {sl_a, sl_b} = i[1:0];
            #10;

            $display("Switch-level: a=%b, b=%b, sum=%b, carry=%b", sl_a, sl_b,
                     sl_sum, sl_carry);
        end
    end
endmodule

different_modeling/half_adder/wave.vcd
$date
	Thu Apr  9 12:55:01 2026
$end
$version
	Icarus Verilog
$end
$timescale
	1s
$end
$scope module half_adder_tb $end
$var wire 1 ! sl_carry $end
$var wire 1 " sl_sum $end
$var wire 1 # gl_sum $end
$var wire 1 $ gl_carry $end
$var wire 1 % df_sum $end
$var wire 1 & df_carry $end
$var wire 1 ' bh_sum $end
$var wire 1 ( bh_carry $end
$var reg 1 ) bh_a $end
$var reg 1 * bh_b $end
$var reg 1 + df_a $end
$var reg 1 , df_b $end
$var reg 1 - gl_a $end
$var reg 1 . gl_b $end
$var reg 1 / sl_a $end
$var reg 1 0 sl_b $end
$scope module bh $end
$var wire 1 ) a $end
$var wire 1 * b $end
$var reg 1 ( carry $end
$var reg 1 ' sum $end
$upscope $end
$scope module df $end
$var wire 1 + a $end
$var wire 1 , b $end
$var wire 1 & carry $end
$var wire 1 % sum $end
$upscope $end
$scope module gl $end
$var wire 1 - a $end
$var wire 1 . b $end
$var wire 1 $ carry $end
$var wire 1 # sum $end
$upscope $end
$scope module sl $end
$var wire 1 / a $end
$var wire 1 1 and_gate2_out $end
$var wire 1 2 and_gate3_out $end
$var wire 1 0 b $end
$var wire 1 ! carry $end
$var wire 1 " sum $end
$scope module and_gate $end
$var wire 1 / a $end
$var wire 1 0 b $end
$var wire 1 3 nand_out $end
$var wire 1 ! out $end
$scope module nand1 $end
$var wire 1 / a $end
$var wire 1 0 b $end
$var wire 1 4 gnd $end
$var wire 1 3 out $end
$var wire 1 5 vcc $end
$var wire 1 6 w1 $end
$upscope $end
$scope module nand2 $end
$var wire 1 3 a $end
$var wire 1 3 b $end
$var wire 1 7 gnd $end
$var wire 1 ! out $end
$var wire 1 8 vcc $end
$var wire 1 9 w1 $end
$upscope $end
$upscope $end
$scope module and_gate2 $end
$var wire 1 / a $end
$var wire 1 : b $end
$var wire 1 ; nor1_out $end
$var wire 1 < nor2_out $end
$var wire 1 1 out $end
$scope module nor1 $end
$var wire 1 / a $end
$var wire 1 / b $end
$var wire 1 = gnd $end
$var wire 1 ; out $end
$var wire 1 > vcc $end
$var wire 1 ? w1 $end
$upscope $end
$scope module nor2 $end
$var wire 1 : a $end
$var wire 1 : b $end
$var wire 1 @ gnd $end
$var wire 1 < out $end
$var wire 1 A vcc $end
$var wire 1 B w1 $end
$upscope $end
$scope module nor3 $end
$var wire 1 ; a $end
$var wire 1 < b $end
$var wire 1 C gnd $end
$var wire 1 1 out $end
$var wire 1 D vcc $end
$var wire 1 E w1 $end
$upscope $end
$upscope $end
$scope module and_gate3 $end
$var wire 1 F a $end
$var wire 1 0 b $end
$var wire 1 G nor1_out $end
$var wire 1 H nor2_out $end
$var wire 1 2 out $end
$scope module nor1 $end
$var wire 1 F a $end
$var wire 1 F b $end
$var wire 1 I gnd $end
$var wire 1 G out $end
$var wire 1 J vcc $end
$var wire 1 K w1 $end
$upscope $end
$scope module nor2 $end
$var wire 1 0 a $end
$var wire 1 0 b $end
$var wire 1 L gnd $end
$var wire 1 H out $end
$var wire 1 M vcc $end
$var wire 1 N w1 $end
$upscope $end
$scope module nor3 $end
$var wire 1 G a $end
$var wire 1 H b $end
$var wire 1 O gnd $end
$var wire 1 2 out $end
$var wire 1 P vcc $end
$var wire 1 Q w1 $end
$upscope $end
$upscope $end
$scope module or_gate $end
$var wire 1 1 a $end
$var wire 1 2 b $end
$var wire 1 R nor_out $end
$var wire 1 " out $end
$scope module nor1 $end
$var wire 1 1 a $end
$var wire 1 2 b $end
$var wire 1 S gnd $end
$var wire 1 R out $end
$var wire 1 T vcc $end
$var wire 1 U w1 $end
$upscope $end
$scope module nor2 $end
$var wire 1 R a $end
$var wire 1 R b $end
$var wire 1 V gnd $end
$var wire 1 " out $end
$var wire 1 W vcc $end
$var wire 1 X w1 $end
$upscope $end
$upscope $end
$upscope $end
$scope begin $ivl_for_loop0 $end
$var integer 32 Y i [31:0] $end
$upscope $end
$scope begin $ivl_for_loop1 $end
$var integer 32 Z i [31:0] $end
$upscope $end
$scope begin $ivl_for_loop2 $end
$var integer 32 [ i [31:0] $end
$upscope $end
$scope begin $ivl_for_loop3 $end
$var integer 32 \ i [31:0] $end
$upscope $end
$upscope $end
$enddefinitions $end
$comment Show the parameter values. $end
$dumpall
$end
#0
$dumpvars
bx \
bx [
bx Z
b0 Y
xX
1W
0V
xU
1T
0S
xR
xQ
1P
0O
xN
1M
0L
xK
1J
0I
xH
xG
xF
xE
1D
0C
xB
1A
0@
x?
1>
0=
x<
x;
x:
x9
18
07
x6
15
04
x3
x2
x1
x0
x/
x.
x-
0,
0+
x*
x)
x(
x'
0&
0%
x$
x#
x"
x!
$end
#10
1%
1,
b1 Y
#20
1+
0,
b10 Y
#30
0%
1&
1,
b11 Y
#40
0(
0'
0)
0*
b0 Z
b100 Y
#50
1'
1*
b1 Z
#60
1)
0*
b10 Z
#70
1(
0'
1*
b11 Z
#80
0#
0$
0-
0.
b0 [
b100 Z
#90
1#
1.
b1 [
#100
1-
0.
b10 [
#110
0#
1$
1.
b11 [
#120
zK
1Q
0G
1F
zB
0<
1:
0"
1U
zX
1R
01
1?
zE
1;
0/
0!
09
13
z6
02
1N
1H
00
b0 \
b100 [
#130
1B
1<
0:
06
zN
1X
1"
0R
12
0H
10
b1 \
#140
1K
zQ
1G
0F
zB
zU
11
0<
1:
z?
1E
0;
1/
z6
1N
1X
1"
0R
02
1H
00
b10 \
#150
1B
1U
zX
0"
1R
01
1<
0:
1!
z9
03
06
zN
0H
10
b11 \
#160
b100 \
