encoders/16x4/design.v
module encoder16x4 (
    input [15:0] in,
    output reg [3:0] out
);

    always @(*) begin
        out = 4'd0;

        for (integer i = 0; i < 16; i++) begin
            if (in[i] && (in != 0) && (in & (in - 1)) == 0) out = i[3:0];
        end
    end

endmodule

encoders/16x4/testbench.v
module testbench;

    reg  [15:0] in;
    wire [ 3:0] out;

    encoder16x4 uut (
        .in (in),
        .out(out)
    );

    initial begin
        $dumpfile("wave.vcd");
        $dumpvars(0, testbench);

        $monitor("in = %b | out = %b", in, out);

        for (integer i = 0; i < (16 * 16); i++) begin
            in = i[15:0];
            #15;
        end

        $finish;
    end
endmodule

encoders/16x4/wave.vcd
$date
	Mon Apr 20 14:25:41 2026
$end
$version
	Icarus Verilog
$end
$timescale
	1s
$end
$scope module testbench $end
$var wire 4 ! out [3:0] $end
$var reg 16 " in [15:0] $end
$scope module uut $end
$var wire 16 # in [15:0] $end
$var reg 4 $ out [3:0] $end
$scope begin $ivl_for_loop0 $end
$var integer 32 % i [31:0] $end
$upscope $end
$upscope $end
$scope begin $ivl_for_loop1 $end
$var integer 32 & i [31:0] $end
$upscope $end
$upscope $end
$enddefinitions $end
$comment Show the parameter values. $end
$dumpall
$end
#0
$dumpvars
b0 &
b10000 %
b0 $
b0 #
b0 "
b0 !
$end
#15
b10000 %
b1 "
b1 #
b1 &
#30
b1 !
b1 $
b10000 %
b10 "
b10 #
b10 &
#45
b10000 %
b0 !
b0 $
b11 "
b11 #
b11 &
#60
b10 !
b10 $
b10000 %
b100 "
b100 #
b100 &
#75
b10000 %
b0 !
b0 $
b101 "
b101 #
b101 &
#90
b10000 %
b110 "
b110 #
b110 &
#105
b10000 %
b111 "
b111 #
b111 &
#120
b11 !
b11 $
b10000 %
b1000 "
b1000 #
b1000 &
#135
b10000 %
b0 !
b0 $
b1001 "
b1001 #
b1001 &
#150
b10000 %
b1010 "
b1010 #
b1010 &
#165
b10000 %
b1011 "
b1011 #
b1011 &
#180
b10000 %
b1100 "
b1100 #
b1100 &
#195
b10000 %
b1101 "
b1101 #
b1101 &
#210
b10000 %
b1110 "
b1110 #
b1110 &
#225
b10000 %
b1111 "
b1111 #
b1111 &
#240
b100 !
b100 $
b10000 %
b10000 "
b10000 #
b10000 &
#255
b10000 %
b0 !
b0 $
b10001 "
b10001 #
b10001 &
#270
b10000 %
b10010 "
b10010 #
b10010 &
#285
b10000 %
b10011 "
b10011 #
b10011 &
#300
b10000 %
b10100 "
b10100 #
b10100 &
#315
b10000 %
b10101 "
b10101 #
b10101 &
#330
b10000 %
b10110 "
b10110 #
b10110 &
#345
b10000 %
b10111 "
b10111 #
b10111 &
#360
b10000 %
b11000 "
b11000 #
b11000 &
#375
b10000 %
b11001 "
b11001 #
b11001 &
#390
b10000 %
b11010 "
b11010 #
b11010 &
#405
b10000 %
b11011 "
b11011 #
b11011 &
#420
b10000 %
b11100 "
b11100 #
b11100 &
#435
b10000 %
b11101 "
b11101 #
b11101 &
#450
b10000 %
b11110 "
b11110 #
b11110 &
#465
b10000 %
b11111 "
b11111 #
b11111 &
#480
b101 !
b101 $
b10000 %
b100000 "
b100000 #
b100000 &
#495
b10000 %
b0 !
b0 $
b100001 "
b100001 #
b100001 &
#510
b10000 %
b100010 "
b100010 #
b100010 &
#525
b10000 %
b100011 "
b100011 #
b100011 &
#540
b10000 %
b100100 "
b100100 #
b100100 &
#555
b10000 %
b100101 "
b100101 #
b100101 &
#570
b10000 %
b100110 "
b100110 #
b100110 &
#585
b10000 %
b100111 "
b100111 #
b100111 &
#600
b10000 %
b101000 "
b101000 #
b101000 &
#615
b10000 %
b101001 "
b101001 #
b101001 &
#630
b10000 %
b101010 "
b101010 #
b101010 &
#645
b10000 %
b101011 "
b101011 #
b101011 &
#660
b10000 %
b101100 "
b101100 #
b101100 &
#675
b10000 %
b101101 "
b101101 #
b101101 &
#690
b10000 %
b101110 "
b101110 #
b101110 &
#705
b10000 %
b101111 "
b101111 #
b101111 &
#720
b10000 %
b110000 "
b110000 #
b110000 &
#735
b10000 %
b110001 "
b110001 #
b110001 &
#750
b10000 %
b110010 "
b110010 #
b110010 &
#765
b10000 %
b110011 "
b110011 #
b110011 &
#780
b10000 %
b110100 "
b110100 #
b110100 &
#795
b10000 %
b110101 "
b110101 #
b110101 &
#810
b10000 %
b110110 "
b110110 #
b110110 &
#825
b10000 %
b110111 "
b110111 #
b110111 &
#840
b10000 %
b111000 "
b111000 #
b111000 &
#855
b10000 %
b111001 "
b111001 #
b111001 &
#870
b10000 %
b111010 "
b111010 #
b111010 &
#885
b10000 %
b111011 "
b111011 #
b111011 &
#900
b10000 %
b111100 "
b111100 #
b111100 &
#915
b10000 %
b111101 "
b111101 #
b111101 &
#930
b10000 %
b111110 "
b111110 #
b111110 &
#945
b10000 %
b111111 "
b111111 #
b111111 &
#960
b110 !
b110 $
b10000 %
b1000000 "
b1000000 #
b1000000 &
#975
b10000 %
b0 !
b0 $
b1000001 "
b1000001 #
b1000001 &
#990
b10000 %
b1000010 "
b1000010 #
b1000010 &
#1005
b10000 %
b1000011 "
b1000011 #
b1000011 &
#1020
b10000 %
b1000100 "
b1000100 #
b1000100 &
#1035
b10000 %
b1000101 "
b1000101 #
b1000101 &
#1050
b10000 %
b1000110 "
b1000110 #
b1000110 &
#1065
b10000 %
b1000111 "
b1000111 #
b1000111 &
#1080
b10000 %
b1001000 "
b1001000 #
b1001000 &
#1095
b10000 %
b1001001 "
b1001001 #
b1001001 &
#1110
b10000 %
b1001010 "
b1001010 #
b1001010 &
#1125
b10000 %
b1001011 "
b1001011 #
b1001011 &
#1140
b10000 %
b1001100 "
b1001100 #
b1001100 &
#1155
b10000 %
b1001101 "
b1001101 #
b1001101 &
#1170
b10000 %
b1001110 "
b1001110 #
b1001110 &
#1185
b10000 %
b1001111 "
b1001111 #
b1001111 &
#1200
b10000 %
b1010000 "
b1010000 #
b1010000 &
#1215
b10000 %
b1010001 "
b1010001 #
b1010001 &
#1230
b10000 %
b1010010 "
b1010010 #
b1010010 &
#1245
b10000 %
b1010011 "
b1010011 #
b1010011 &
#1260
b10000 %
b1010100 "
b1010100 #
b1010100 &
#1275
b10000 %
b1010101 "
b1010101 #
b1010101 &
#1290
b10000 %
b1010110 "
b1010110 #
b1010110 &
#1305
b10000 %
b1010111 "
b1010111 #
b1010111 &
#1320
b10000 %
b1011000 "
b1011000 #
b1011000 &
#1335
b10000 %
b1011001 "
b1011001 #
b1011001 &
#1350
b10000 %
b1011010 "
b1011010 #
b1011010 &
#1365
b10000 %
b1011011 "
b1011011 #
b1011011 &
#1380
b10000 %
b1011100 "
b1011100 #
b1011100 &
#1395
b10000 %
b1011101 "
b1011101 #
b1011101 &
#1410
b10000 %
b1011110 "
b1011110 #
b1011110 &
#1425
b10000 %
b1011111 "
b1011111 #
b1011111 &
#1440
b10000 %
b1100000 "
b1100000 #
b1100000 &
#1455
b10000 %
b1100001 "
b1100001 #
b1100001 &
#1470
b10000 %
b1100010 "
b1100010 #
b1100010 &
#1485
b10000 %
b1100011 "
b1100011 #
b1100011 &
#1500
b10000 %
b1100100 "
b1100100 #
b1100100 &
#1515
b10000 %
b1100101 "
b1100101 #
b1100101 &
#1530
b10000 %
b1100110 "
b1100110 #
b1100110 &
#1545
b10000 %
b1100111 "
b1100111 #
b1100111 &
#1560
b10000 %
b1101000 "
b1101000 #
b1101000 &
#1575
b10000 %
b1101001 "
b1101001 #
b1101001 &
#1590
b10000 %
b1101010 "
b1101010 #
b1101010 &
#1605
b10000 %
b1101011 "
b1101011 #
b1101011 &
#1620
b10000 %
b1101100 "
b1101100 #
b1101100 &
#1635
b10000 %
b1101101 "
b1101101 #
b1101101 &
#1650
b10000 %
b1101110 "
b1101110 #
b1101110 &
#1665
b10000 %
b1101111 "
b1101111 #
b1101111 &
#1680
b10000 %
b1110000 "
b1110000 #
b1110000 &
#1695
b10000 %
b1110001 "
b1110001 #
b1110001 &
#1710
b10000 %
b1110010 "
b1110010 #
b1110010 &
#1725
b10000 %
b1110011 "
b1110011 #
b1110011 &
#1740
b10000 %
b1110100 "
b1110100 #
b1110100 &
#1755
b10000 %
b1110101 "
b1110101 #
b1110101 &
#1770
b10000 %
b1110110 "
b1110110 #
b1110110 &
#1785
b10000 %
b1110111 "
b1110111 #
b1110111 &
#1800
b10000 %
b1111000 "
b1111000 #
b1111000 &
#1815
b10000 %
b1111001 "
b1111001 #
b1111001 &
#1830
b10000 %
b1111010 "
b1111010 #
b1111010 &
#1845
b10000 %
b1111011 "
b1111011 #
b1111011 &
#1860
b10000 %
b1111100 "
b1111100 #
b1111100 &
#1875
b10000 %
b1111101 "
b1111101 #
b1111101 &
#1890
b10000 %
b1111110 "
b1111110 #
b1111110 &
#1905
b10000 %
b1111111 "
b1111111 #
b1111111 &
#1920
b111 !
b111 $
b10000 %
b10000000 "
b10000000 #
b10000000 &
#1935
b10000 %
b0 !
b0 $
b10000001 "
b10000001 #
b10000001 &
#1950
b10000 %
b10000010 "
b10000010 #
b10000010 &
#1965
b10000 %
b10000011 "
b10000011 #
b10000011 &
#1980
b10000 %
b10000100 "
b10000100 #
b10000100 &
#1995
b10000 %
b10000101 "
b10000101 #
b10000101 &
#2010
b10000 %
b10000110 "
b10000110 #
b10000110 &
#2025
b10000 %
b10000111 "
b10000111 #
b10000111 &
#2040
b10000 %
b10001000 "
b10001000 #
b10001000 &
#2055
b10000 %
b10001001 "
b10001001 #
b10001001 &
#2070
b10000 %
b10001010 "
b10001010 #
b10001010 &
#2085
b10000 %
b10001011 "
b10001011 #
b10001011 &
#2100
b10000 %
b10001100 "
b10001100 #
b10001100 &
#2115
b10000 %
b10001101 "
b10001101 #
b10001101 &
#2130
b10000 %
b10001110 "
b10001110 #
b10001110 &
#2145
b10000 %
b10001111 "
b10001111 #
b10001111 &
#2160
b10000 %
b10010000 "
b10010000 #
b10010000 &
#2175
b10000 %
b10010001 "
b10010001 #
b10010001 &
#2190
b10000 %
b10010010 "
b10010010 #
b10010010 &
#2205
b10000 %
b10010011 "
b10010011 #
b10010011 &
#2220
b10000 %
b10010100 "
b10010100 #
b10010100 &
#2235
b10000 %
b10010101 "
b10010101 #
b10010101 &
#2250
b10000 %
b10010110 "
b10010110 #
b10010110 &
#2265
b10000 %
b10010111 "
b10010111 #
b10010111 &
#2280
b10000 %
b10011000 "
b10011000 #
b10011000 &
#2295
b10000 %
b10011001 "
b10011001 #
b10011001 &
#2310
b10000 %
b10011010 "
b10011010 #
b10011010 &
#2325
b10000 %
b10011011 "
b10011011 #
b10011011 &
#2340
b10000 %
b10011100 "
b10011100 #
b10011100 &
#2355
b10000 %
b10011101 "
b10011101 #
b10011101 &
#2370
b10000 %
b10011110 "
b10011110 #
b10011110 &
#2385
b10000 %
b10011111 "
b10011111 #
b10011111 &
#2400
b10000 %
b10100000 "
b10100000 #
b10100000 &
#2415
b10000 %
b10100001 "
b10100001 #
b10100001 &
#2430
b10000 %
b10100010 "
b10100010 #
b10100010 &
#2445
b10000 %
b10100011 "
b10100011 #
b10100011 &
#2460
b10000 %
b10100100 "
b10100100 #
b10100100 &
#2475
b10000 %
b10100101 "
b10100101 #
b10100101 &
#2490
b10000 %
b10100110 "
b10100110 #
b10100110 &
#2505
b10000 %
b10100111 "
b10100111 #
b10100111 &
#2520
b10000 %
b10101000 "
b10101000 #
b10101000 &
#2535
b10000 %
b10101001 "
b10101001 #
b10101001 &
#2550
b10000 %
b10101010 "
b10101010 #
b10101010 &
#2565
b10000 %
b10101011 "
b10101011 #
b10101011 &
#2580
b10000 %
b10101100 "
b10101100 #
b10101100 &
#2595
b10000 %
b10101101 "
b10101101 #
b10101101 &
#2610
b10000 %
b10101110 "
b10101110 #
b10101110 &
#2625
b10000 %
b10101111 "
b10101111 #
b10101111 &
#2640
b10000 %
b10110000 "
b10110000 #
b10110000 &
#2655
b10000 %
b10110001 "
b10110001 #
b10110001 &
#2670
b10000 %
b10110010 "
b10110010 #
b10110010 &
#2685
b10000 %
b10110011 "
b10110011 #
b10110011 &
#2700
b10000 %
b10110100 "
b10110100 #
b10110100 &
#2715
b10000 %
b10110101 "
b10110101 #
b10110101 &
#2730
b10000 %
b10110110 "
b10110110 #
b10110110 &
#2745
b10000 %
b10110111 "
b10110111 #
b10110111 &
#2760
b10000 %
b10111000 "
b10111000 #
b10111000 &
#2775
b10000 %
b10111001 "
b10111001 #
b10111001 &
#2790
b10000 %
b10111010 "
b10111010 #
b10111010 &
#2805
b10000 %
b10111011 "
b10111011 #
b10111011 &
#2820
b10000 %
b10111100 "
b10111100 #
b10111100 &
#2835
b10000 %
b10111101 "
b10111101 #
b10111101 &
#2850
b10000 %
b10111110 "
b10111110 #
b10111110 &
#2865
b10000 %
b10111111 "
b10111111 #
b10111111 &
#2880
b10000 %
b11000000 "
b11000000 #
b11000000 &
#2895
b10000 %
b11000001 "
b11000001 #
b11000001 &
#2910
b10000 %
b11000010 "
b11000010 #
b11000010 &
#2925
b10000 %
b11000011 "
b11000011 #
b11000011 &
#2940
b10000 %
b11000100 "
b11000100 #
b11000100 &
#2955
b10000 %
b11000101 "
b11000101 #
b11000101 &
#2970
b10000 %
b11000110 "
b11000110 #
b11000110 &
#2985
b10000 %
b11000111 "
b11000111 #
b11000111 &
#3000
b10000 %
b11001000 "
b11001000 #
b11001000 &
#3015
b10000 %
b11001001 "
b11001001 #
b11001001 &
#3030
b10000 %
b11001010 "
b11001010 #
b11001010 &
#3045
b10000 %
b11001011 "
b11001011 #
b11001011 &
#3060
b10000 %
b11001100 "
b11001100 #
b11001100 &
#3075
b10000 %
b11001101 "
b11001101 #
b11001101 &
#3090
b10000 %
b11001110 "
b11001110 #
b11001110 &
#3105
b10000 %
b11001111 "
b11001111 #
b11001111 &
#3120
b10000 %
b11010000 "
b11010000 #
b11010000 &
#3135
b10000 %
b11010001 "
b11010001 #
b11010001 &
#3150
b10000 %
b11010010 "
b11010010 #
b11010010 &
#3165
b10000 %
b11010011 "
b11010011 #
b11010011 &
#3180
b10000 %
b11010100 "
b11010100 #
b11010100 &
#3195
b10000 %
b11010101 "
b11010101 #
b11010101 &
#3210
b10000 %
b11010110 "
b11010110 #
b11010110 &
#3225
b10000 %
b11010111 "
b11010111 #
b11010111 &
#3240
b10000 %
b11011000 "
b11011000 #
b11011000 &
#3255
b10000 %
b11011001 "
b11011001 #
b11011001 &
#3270
b10000 %
b11011010 "
b11011010 #
b11011010 &
#3285
b10000 %
b11011011 "
b11011011 #
b11011011 &
#3300
b10000 %
b11011100 "
b11011100 #
b11011100 &
#3315
b10000 %
b11011101 "
b11011101 #
b11011101 &
#3330
b10000 %
b11011110 "
b11011110 #
b11011110 &
#3345
b10000 %
b11011111 "
b11011111 #
b11011111 &
#3360
b10000 %
b11100000 "
b11100000 #
b11100000 &
#3375
b10000 %
b11100001 "
b11100001 #
b11100001 &
#3390
b10000 %
b11100010 "
b11100010 #
b11100010 &
#3405
b10000 %
b11100011 "
b11100011 #
b11100011 &
#3420
b10000 %
b11100100 "
b11100100 #
b11100100 &
#3435
b10000 %
b11100101 "
b11100101 #
b11100101 &
#3450
b10000 %
b11100110 "
b11100110 #
b11100110 &
#3465
b10000 %
b11100111 "
b11100111 #
b11100111 &
#3480
b10000 %
b11101000 "
b11101000 #
b11101000 &
#3495
b10000 %
b11101001 "
b11101001 #
b11101001 &
#3510
b10000 %
b11101010 "
b11101010 #
b11101010 &
#3525
b10000 %
b11101011 "
b11101011 #
b11101011 &
#3540
b10000 %
b11101100 "
b11101100 #
b11101100 &
#3555
b10000 %
b11101101 "
b11101101 #
b11101101 &
#3570
b10000 %
b11101110 "
b11101110 #
b11101110 &
#3585
b10000 %
b11101111 "
b11101111 #
b11101111 &
#3600
b10000 %
b11110000 "
b11110000 #
b11110000 &
#3615
b10000 %
b11110001 "
b11110001 #
b11110001 &
#3630
b10000 %
b11110010 "
b11110010 #
b11110010 &
#3645
b10000 %
b11110011 "
b11110011 #
b11110011 &
#3660
b10000 %
b11110100 "
b11110100 #
b11110100 &
#3675
b10000 %
b11110101 "
b11110101 #
b11110101 &
#3690
b10000 %
b11110110 "
b11110110 #
b11110110 &
#3705
b10000 %
b11110111 "
b11110111 #
b11110111 &
#3720
b10000 %
b11111000 "
b11111000 #
b11111000 &
#3735
b10000 %
b11111001 "
b11111001 #
b11111001 &
#3750
b10000 %
b11111010 "
b11111010 #
b11111010 &
#3765
b10000 %
b11111011 "
b11111011 #
b11111011 &
#3780
b10000 %
b11111100 "
b11111100 #
b11111100 &
#3795
b10000 %
b11111101 "
b11111101 #
b11111101 &
#3810
b10000 %
b11111110 "
b11111110 #
b11111110 &
#3825
b10000 %
b11111111 "
b11111111 #
b11111111 &
#3840
b100000000 &
